{"box_data": [{"position": {"minX": 495.75, "minY": 126.0, "maxX": 531.5, "maxY": 143.0}, "class_id": 2, "box_caption": "large_D 0.948", "scores": {"class_score": 0.9482421875}, "domain": "pixel"}, {"position": {"minX": 610.5, "minY": 233.625, "maxX": 616.5, "maxY": 241.875}, "class_id": 1, "box_caption": "small_D 0.683", "scores": {"class_score": 0.68310546875}, "domain": "pixel"}, {"position": {"minX": 610.5, "minY": 233.625, "maxX": 616.5, "maxY": 242.125}, "class_id": 0, "box_caption": "medium_D 0.175", "scores": {"class_score": 0.175048828125}, "domain": "pixel"}, {"position": {"minX": 610.5, "minY": 233.625, "maxX": 616.5, "maxY": 242.125}, "class_id": 2, "box_caption": "large_D 0.012", "scores": {"class_score": 0.0119476318359375}, "domain": "pixel"}, {"position": {"minX": 122.75, "minY": 231.5, "maxX": 138.25, "maxY": 234.0}, "class_id": 0, "box_caption": "medium_D 0.009", "scores": {"class_score": 0.0089263916015625}, "domain": "pixel"}, {"position": {"minX": 323.25, "minY": 234.875, "maxX": 344.25, "maxY": 239.625}, "class_id": 0, "box_caption": "medium_D 0.006", "scores": {"class_score": 0.006206512451171875}, "domain": "pixel"}, {"position": {"minX": 495.75, "minY": 125.9375, "maxX": 531.0, "maxY": 143.0}, "class_id": 18, "box_caption": "F1 0.003", "scores": {"class_score": 0.0034503936767578125}, "domain": "pixel"}, {"position": {"minX": 495.75, "minY": 125.9375, "maxX": 531.0, "maxY": 143.0}, "class_id": 0, "box_caption": "medium_D 0.002", "scores": {"class_score": 0.002231597900390625}, "domain": "pixel"}, {"position": {"minX": 496.0, "minY": 126.0, "maxX": 531.0, "maxY": 143.0}, "class_id": 16, "box_caption": "moto_gp 0.002", "scores": {"class_score": 0.0021266937255859375}, "domain": "pixel"}, {"position": {"minX": 609.0, "minY": 233.5, "maxX": 615.0, "maxY": 242.0}, "class_id": 1, "box_caption": "small_D 0.002", "scores": {"class_score": 0.0017719268798828125}, "domain": "pixel"}, {"position": {"minX": 122.75, "minY": 231.5, "maxX": 138.25, "maxY": 234.0}, "class_id": 1, "box_caption": "small_D 0.002", "scores": {"class_score": 0.0015888214111328125}, "domain": "pixel"}, {"position": {"minX": 496.0, "minY": 126.0625, "maxX": 531.0, "maxY": 143.25}, "class_id": 9, "box_caption": "marshall 0.001", "scores": {"class_score": 0.0010957717895507812}, "domain": "pixel"}, {"position": {"minX": 496.0, "minY": 126.0625, "maxX": 531.0, "maxY": 143.25}, "class_id": 33, "box_caption": "nascar 0.001", "scores": {"class_score": 0.001079559326171875}, "domain": "pixel"}, {"position": {"minX": 496.0, "minY": 126.0625, "maxX": 531.0, "maxY": 143.25}, "class_id": 6, "box_caption": "pilot_falling 0.001", "scores": {"class_score": 0.0010747909545898438}, "domain": "pixel"}, {"position": {"minX": 496.0, "minY": 126.0625, "maxX": 531.0, "maxY": 143.25}, "class_id": 24, "box_caption": "LMP 0.001", "scores": {"class_score": 0.0010709762573242188}, "domain": "pixel"}, {"position": {"minX": 496.0, "minY": 126.0625, "maxX": 531.0, "maxY": 143.25}, "class_id": 55, "box_caption": "conc_wall 0.001", "scores": {"class_score": 0.0010709762573242188}, "domain": "pixel"}, {"position": {"minX": 496.0, "minY": 126.0625, "maxX": 531.0, "maxY": 143.25}, "class_id": 69, "box_caption": "wall 0.001", "scores": {"class_score": 0.0010709762573242188}, "domain": "pixel"}, {"position": {"minX": 496.0, "minY": 126.0625, "maxX": 531.0, "maxY": 143.25}, "class_id": 20, "box_caption": "F3 0.001", "scores": {"class_score": 0.0010614395141601562}, "domain": "pixel"}, {"position": {"minX": 496.0, "minY": 126.0625, "maxX": 531.0, "maxY": 143.25}, "class_id": 49, "box_caption": "brakD_S_150 0.001", "scores": {"class_score": 0.0010614395141601562}, "domain": "pixel"}, {"position": {"minX": 496.0, "minY": 126.0625, "maxX": 531.0, "maxY": 143.25}, "class_id": 25, "box_caption": "GT 0.001", "scores": {"class_score": 0.0010585784912109375}, "domain": "pixel"}, {"position": {"minX": 496.0, "minY": 126.0625, "maxX": 531.0, "maxY": 143.25}, "class_id": 42, "box_caption": "chequered_F 0.001", "scores": {"class_score": 0.0010538101196289062}, "domain": "pixel"}, {"position": {"minX": 496.0, "minY": 126.0625, "maxX": 531.0, "maxY": 143.25}, "class_id": 73, "box_caption": "barrier 0.001", "scores": {"class_score": 0.0010538101196289062}, "domain": "pixel"}, {"position": {"minX": 496.0, "minY": 126.0625, "maxX": 531.0, "maxY": 143.25}, "class_id": 74, "box_caption": "house 0.001", "scores": {"class_score": 0.0010538101196289062}, "domain": "pixel"}, {"position": {"minX": 496.0, "minY": 126.0625, "maxX": 531.0, "maxY": 143.25}, "class_id": 57, "box_caption": "fencing 0.001", "scores": {"class_score": 0.0010499954223632812}, "domain": "pixel"}, {"position": {"minX": 496.0, "minY": 126.0625, "maxX": 531.0, "maxY": 143.25}, "class_id": 64, "box_caption": "sand 0.001", "scores": {"class_score": 0.00104522705078125}, "domain": "pixel"}, {"position": {"minX": 496.0, "minY": 126.0625, "maxX": 531.0, "maxY": 143.25}, "class_id": 3, "box_caption": "pilot_standing 0.001", "scores": {"class_score": 0.00104522705078125}, "domain": "pixel"}, {"position": {"minX": 496.0, "minY": 126.0625, "maxX": 531.0, "maxY": 143.25}, "class_id": 19, "box_caption": "F2 0.001", "scores": {"class_score": 0.00104522705078125}, "domain": "pixel"}, {"position": {"minX": 496.0, "minY": 126.0625, "maxX": 531.0, "maxY": 143.25}, "class_id": 27, "box_caption": "wrc 0.001", "scores": {"class_score": 0.00104522705078125}, "domain": "pixel"}, {"position": {"minX": 496.0, "minY": 126.0625, "maxX": 531.0, "maxY": 143.25}, "class_id": 36, "box_caption": "yellow_flag 0.001", "scores": {"class_score": 0.0010423660278320312}, "domain": "pixel"}, {"position": {"minX": 496.0, "minY": 126.0625, "maxX": 531.0, "maxY": 143.25}, "class_id": 68, "box_caption": "barrier_tape 0.001", "scores": {"class_score": 0.0010423660278320312}, "domain": "pixel"}, {"position": {"minX": 496.0, "minY": 126.0625, "maxX": 531.0, "maxY": 143.25}, "class_id": 76, "box_caption": "lollipop 0.001", "scores": {"class_score": 0.0010423660278320312}, "domain": "pixel"}, {"position": {"minX": 496.0, "minY": 126.0625, "maxX": 531.0, "maxY": 143.25}, "class_id": 22, "box_caption": "FE 0.001", "scores": {"class_score": 0.0010423660278320312}, "domain": "pixel"}, {"position": {"minX": 496.0, "minY": 126.0625, "maxX": 531.0, "maxY": 143.25}, "class_id": 54, "box_caption": "start_fin_line 0.001", "scores": {"class_score": 0.0010423660278320312}, "domain": "pixel"}, {"position": {"minX": 496.0, "minY": 126.0625, "maxX": 531.0, "maxY": 143.25}, "class_id": 37, "box_caption": "red_flag 0.001", "scores": {"class_score": 0.0010423660278320312}, "domain": "pixel"}, {"position": {"minX": 496.0, "minY": 126.0625, "maxX": 531.0, "maxY": 143.25}, "class_id": 67, "box_caption": "jump 0.001", "scores": {"class_score": 0.00103759765625}, "domain": "pixel"}, {"position": {"minX": 496.0, "minY": 126.0625, "maxX": 531.0, "maxY": 143.25}, "class_id": 31, "box_caption": "rraid_Baja 0.001", "scores": {"class_score": 0.00103759765625}, "domain": "pixel"}, {"position": {"minX": 496.0, "minY": 126.0625, "maxX": 531.0, "maxY": 143.25}, "class_id": 60, "box_caption": "cones 0.001", "scores": {"class_score": 0.00103759765625}, "domain": "pixel"}, {"position": {"minX": 496.0, "minY": 126.0625, "maxX": 531.0, "maxY": 143.25}, "class_id": 23, "box_caption": "Indy 0.001", "scores": {"class_score": 0.00103759765625}, "domain": "pixel"}, {"position": {"minX": 496.0, "minY": 126.0625, "maxX": 531.0, "maxY": 143.25}, "class_id": 59, "box_caption": "grass 0.001", "scores": {"class_score": 0.00103759765625}, "domain": "pixel"}, {"position": {"minX": 496.0, "minY": 126.0625, "maxX": 531.0, "maxY": 143.25}, "class_id": 66, "box_caption": "hole 0.001", "scores": {"class_score": 0.0010328292846679688}, "domain": "pixel"}, {"position": {"minX": 496.0, "minY": 126.0625, "maxX": 531.0, "maxY": 143.25}, "class_id": 15, "box_caption": "safety_car 0.001", "scores": {"class_score": 0.0010328292846679688}, "domain": "pixel"}, {"position": {"minX": 496.0, "minY": 126.0625, "maxX": 531.0, "maxY": 143.25}, "class_id": 34, "box_caption": "sprint_car 0.001", "scores": {"class_score": 0.0010328292846679688}, "domain": "pixel"}, {"position": {"minX": 496.0, "minY": 126.0625, "maxX": 531.0, "maxY": 143.25}, "class_id": 51, "box_caption": "kerbs 0.001", "scores": {"class_score": 0.0010328292846679688}, "domain": "pixel"}, {"position": {"minX": 495.75, "minY": 126.0, "maxX": 531.5, "maxY": 143.0}, "class_id": 1, "box_caption": "small_D 0.001", "scores": {"class_score": 0.0010309219360351562}, "domain": "pixel"}, {"position": {"minX": 496.0, "minY": 126.0625, "maxX": 531.0, "maxY": 143.25}, "class_id": 70, "box_caption": "dune 0.001", "scores": {"class_score": 0.00102996826171875}, "domain": "pixel"}, {"position": {"minX": 496.0, "minY": 126.0625, "maxX": 531.0, "maxY": 143.25}, "class_id": 7, "box_caption": "pilot_sliding 0.001", "scores": {"class_score": 0.00102996826171875}, "domain": "pixel"}, {"position": {"minX": 496.0, "minY": 126.0625, "maxX": 531.0, "maxY": 143.25}, "class_id": 63, "box_caption": "mud 0.001", "scores": {"class_score": 0.00102996826171875}, "domain": "pixel"}, {"position": {"minX": 496.0, "minY": 126.0625, "maxX": 531.0, "maxY": 143.25}, "class_id": 8, "box_caption": "pilot_injured 0.001", "scores": {"class_score": 0.00102996826171875}, "domain": "pixel"}, {"position": {"minX": 496.0, "minY": 126.0625, "maxX": 531.0, "maxY": 143.25}, "class_id": 32, "box_caption": "rraid_XE 0.001", "scores": {"class_score": 0.00102996826171875}, "domain": "pixel"}, {"position": {"minX": 496.0, "minY": 126.0625, "maxX": 531.0, "maxY": 143.25}, "class_id": 45, "box_caption": "tarmac 0.001", "scores": {"class_score": 0.0010251998901367188}, "domain": "pixel"}, {"position": {"minX": 496.0, "minY": 126.0625, "maxX": 531.0, "maxY": 143.25}, "class_id": 53, "box_caption": "lines 0.001", "scores": {"class_score": 0.0010251998901367188}, "domain": "pixel"}, {"position": {"minX": 496.0, "minY": 126.0625, "maxX": 531.0, "maxY": 143.25}, "class_id": 13, "box_caption": "helmet_open 0.001", "scores": {"class_score": 0.0010251998901367188}, "domain": "pixel"}, {"position": {"minX": 496.0, "minY": 126.0625, "maxX": 531.0, "maxY": 143.25}, "class_id": 28, "box_caption": "wrx 0.001", "scores": {"class_score": 0.0010251998901367188}, "domain": "pixel"}, {"position": {"minX": 496.0, "minY": 126.0625, "maxX": 531.0, "maxY": 143.25}, "class_id": 38, "box_caption": "redyellow_F 0.001", "scores": {"class_score": 0.0010213851928710938}, "domain": "pixel"}, {"position": {"minX": 496.0, "minY": 126.0625, "maxX": 531.0, "maxY": 143.25}, "class_id": 30, "box_caption": "rraid_Dakar 0.001", "scores": {"class_score": 0.0010213851928710938}, "domain": "pixel"}, {"position": {"minX": 496.0, "minY": 126.0625, "maxX": 531.0, "maxY": 143.25}, "class_id": 14, "box_caption": "helmet_fullX 0.001", "scores": {"class_score": 0.0010213851928710938}, "domain": "pixel"}, {"position": {"minX": 496.0, "minY": 126.0625, "maxX": 531.0, "maxY": 143.25}, "class_id": 17, "box_caption": "moto_x 0.001", "scores": {"class_score": 0.0010213851928710938}, "domain": "pixel"}, {"position": {"minX": 496.0, "minY": 126.0625, "maxX": 531.0, "maxY": 143.25}, "class_id": 10, "box_caption": "team_crew 0.001", "scores": {"class_score": 0.0010213851928710938}, "domain": "pixel"}, {"position": {"minX": 496.0, "minY": 126.0625, "maxX": 531.0, "maxY": 143.25}, "class_id": 29, "box_caption": "wtcr 0.001", "scores": {"class_score": 0.0010175704956054688}, "domain": "pixel"}, {"position": {"minX": 496.0, "minY": 126.0625, "maxX": 531.0, "maxY": 143.25}, "class_id": 61, "box_caption": "smock 0.001", "scores": {"class_score": 0.0010175704956054688}, "domain": "pixel"}, {"position": {"minX": 496.0, "minY": 126.0625, "maxX": 531.0, "maxY": 143.25}, "class_id": 44, "box_caption": "red_lights 0.001", "scores": {"class_score": 0.0010175704956054688}, "domain": "pixel"}, {"position": {"minX": 496.0, "minY": 126.0625, "maxX": 531.0, "maxY": 143.25}, "class_id": 26, "box_caption": "wtcr 0.001", "scores": {"class_score": 0.0010175704956054688}, "domain": "pixel"}, {"position": {"minX": 496.0, "minY": 126.0625, "maxX": 531.0, "maxY": 143.25}, "class_id": 48, "box_caption": "brakD_S_100 0.001", "scores": {"class_score": 0.0010175704956054688}, "domain": "pixel"}, {"position": {"minX": 496.0, "minY": 126.0625, "maxX": 531.0, "maxY": 143.25}, "class_id": 12, "box_caption": "helmet_full 0.001", "scores": {"class_score": 0.0010175704956054688}, "domain": "pixel"}, {"position": {"minX": 496.0, "minY": 126.0625, "maxX": 531.0, "maxY": 143.25}, "class_id": 4, "box_caption": "pilot_walking 0.001", "scores": {"class_score": 0.0010137557983398438}, "domain": "pixel"}, {"position": {"minX": 496.0, "minY": 126.0625, "maxX": 531.0, "maxY": 143.25}, "class_id": 39, "box_caption": "blue_flag 0.001", "scores": {"class_score": 0.0010137557983398438}, "domain": "pixel"}, {"position": {"minX": 496.0, "minY": 126.0625, "maxX": 531.0, "maxY": 143.25}, "class_id": 75, "box_caption": "car 0.001", "scores": {"class_score": 0.0010137557983398438}, "domain": "pixel"}, {"position": {"minX": 496.0, "minY": 126.0625, "maxX": 531.0, "maxY": 143.25}, "class_id": 50, "box_caption": "apex 0.001", "scores": {"class_score": 0.0010137557983398438}, "domain": "pixel"}, {"position": {"minX": 496.0, "minY": 126.0625, "maxX": 531.0, "maxY": 143.25}, "class_id": 41, "box_caption": "blackwhite_F 0.001", "scores": {"class_score": 0.0010099411010742188}, "domain": "pixel"}, {"position": {"minX": 496.0, "minY": 126.0625, "maxX": 531.0, "maxY": 143.25}, "class_id": 56, "box_caption": "chocabs_wall 0.001", "scores": {"class_score": 0.0010099411010742188}, "domain": "pixel"}, {"position": {"minX": 496.0, "minY": 126.0625, "maxX": 531.0, "maxY": 143.25}, "class_id": 5, "box_caption": "pilot_racing 0.001", "scores": {"class_score": 0.0010051727294921875}, "domain": "pixel"}, {"position": {"minX": 496.0, "minY": 126.0625, "maxX": 531.0, "maxY": 143.25}, "class_id": 71, "box_caption": "tree 0.001", "scores": {"class_score": 0.0010051727294921875}, "domain": "pixel"}, {"position": {"minX": 496.0, "minY": 126.0625, "maxX": 531.0, "maxY": 143.25}, "class_id": 40, "box_caption": "black_flag 0.001", "scores": {"class_score": 0.0010051727294921875}, "domain": "pixel"}, {"position": {"minX": 496.0, "minY": 126.0625, "maxX": 531.0, "maxY": 143.25}, "class_id": 65, "box_caption": "snow_ice 0.001", "scores": {"class_score": 0.0010051727294921875}, "domain": "pixel"}, {"position": {"minX": 496.0, "minY": 126.0625, "maxX": 531.0, "maxY": 143.25}, "class_id": 72, "box_caption": "stone 0.001", "scores": {"class_score": 0.0010023117065429688}, "domain": "pixel"}, {"position": {"minX": 496.0, "minY": 126.0625, "maxX": 531.0, "maxY": 143.25}, "class_id": 43, "box_caption": "green_lights 0.001", "scores": {"class_score": 0.0010023117065429688}, "domain": "pixel"}], "class_labels": {"0": "medium_D", "1": "small_D", "2": "large_D", "3": "pilot_standing", "4": "pilot_walking", "5": "pilot_racing", "6": "pilot_falling", "7": "pilot_sliding", "8": "pilot_injured", "9": "marshall", "10": "team_crew", "11": "spectator", "12": "helmet_full", "13": "helmet_open", "14": "helmet_fullX", "15": "safety_car", "16": "moto_gp", "17": "moto_x", "18": "F1", "19": "F2", "20": "F3", "21": "F4", "22": "FE", "23": "Indy", "24": "LMP", "25": "GT", "26": "wtcr", "27": "wrc", "28": "wrx", "29": "wtcr", "30": "rraid_Dakar", "31": "rraid_Baja", "32": "rraid_XE", "33": "nascar", "34": "sprint_car", "35": "green_flag", "36": "yellow_flag", "37": "red_flag", "38": "redyellow_F", "39": "blue_flag", "40": "black_flag", "41": "blackwhite_F", "42": "chequered_F", "43": "green_lights", "44": "red_lights", "45": "tarmac", "46": "gravel", "47": "brakD_S_50", "48": "brakD_S_100", "49": "brakD_S_150", "50": "apex", "51": "kerbs", "52": "lane", "53": "lines", "54": "start_fin_line", "55": "conc_wall", "56": "chocabs_wall", "57": "fencing", "58": "run_off", "59": "grass", "60": "cones", "61": "smock", "62": "oil", "63": "mud", "64": "sand", "65": "snow_ice", "66": "hole", "67": "jump", "68": "barrier_tape", "69": "wall", "70": "dune", "71": "tree", "72": "stone", "73": "barrier", "74": "house", "75": "car", "76": "lollipop"}}