{"box_data": [{"position": {"minX": 464.0, "minY": 142.75, "maxX": 554.5, "maxY": 209.5}, "class_id": 2, "box_caption": "large_D 0.977", "scores": {"class_score": 0.97705078125}, "domain": "pixel"}, {"position": {"minX": 379.0, "minY": 220.125, "maxX": 414.0, "maxY": 237.375}, "class_id": 2, "box_caption": "large_D 0.948", "scores": {"class_score": 0.94775390625}, "domain": "pixel"}, {"position": {"minX": 354.0, "minY": 72.6875, "maxX": 366.0, "maxY": 91.3125}, "class_id": 0, "box_caption": "medium_D 0.937", "scores": {"class_score": 0.9365234375}, "domain": "pixel"}, {"position": {"minX": 51.21875, "minY": 276.75, "maxX": 72.5, "maxY": 293.25}, "class_id": 2, "box_caption": "large_D 0.936", "scores": {"class_score": 0.93603515625}, "domain": "pixel"}, {"position": {"minX": 600.0, "minY": 260.5, "maxX": 608.0, "maxY": 289.5}, "class_id": 0, "box_caption": "medium_D 0.930", "scores": {"class_score": 0.9296875}, "domain": "pixel"}, {"position": {"minX": 495.0, "minY": 62.96875, "maxX": 515.5, "maxY": 73.875}, "class_id": 0, "box_caption": "medium_D 0.926", "scores": {"class_score": 0.92626953125}, "domain": "pixel"}, {"position": {"minX": 603.5, "minY": 139.25, "maxX": 622.5, "maxY": 151.0}, "class_id": 0, "box_caption": "medium_D 0.924", "scores": {"class_score": 0.923828125}, "domain": "pixel"}, {"position": {"minX": 246.875, "minY": 216.25, "maxX": 270.25, "maxY": 224.25}, "class_id": 0, "box_caption": "medium_D 0.919", "scores": {"class_score": 0.9189453125}, "domain": "pixel"}, {"position": {"minX": 90.9375, "minY": 90.75, "maxX": 96.5625, "maxY": 102.625}, "class_id": 0, "box_caption": "medium_D 0.913", "scores": {"class_score": 0.91259765625}, "domain": "pixel"}, {"position": {"minX": 507.75, "minY": 132.625, "maxX": 522.0, "maxY": 135.875}, "class_id": 0, "box_caption": "medium_D 0.884", "scores": {"class_score": 0.88427734375}, "domain": "pixel"}, {"position": {"minX": 305.25, "minY": 253.125, "maxX": 331.75, "maxY": 257.0}, "class_id": 0, "box_caption": "medium_D 0.876", "scores": {"class_score": 0.87646484375}, "domain": "pixel"}, {"position": {"minX": 32.78125, "minY": 197.75, "maxX": 51.96875, "maxY": 200.25}, "class_id": 0, "box_caption": "medium_D 0.849", "scores": {"class_score": 0.8486328125}, "domain": "pixel"}, {"position": {"minX": 323.25, "minY": 40.46875, "maxX": 327.75, "maxY": 44.53125}, "class_id": 1, "box_caption": "small_D 0.804", "scores": {"class_score": 0.80419921875}, "domain": "pixel"}, {"position": {"minX": 312.25, "minY": 272.25, "maxX": 316.75, "maxY": 274.75}, "class_id": 1, "box_caption": "small_D 0.312", "scores": {"class_score": 0.31201171875}, "domain": "pixel"}, {"position": {"minX": 311.5, "minY": 272.0, "maxX": 316.5, "maxY": 274.5}, "class_id": 0, "box_caption": "medium_D 0.092", "scores": {"class_score": 0.09173583984375}, "domain": "pixel"}, {"position": {"minX": 199.125, "minY": 248.25, "maxX": 211.375, "maxY": 250.5}, "class_id": 0, "box_caption": "medium_D 0.056", "scores": {"class_score": 0.05560302734375}, "domain": "pixel"}, {"position": {"minX": 199.125, "minY": 248.25, "maxX": 211.375, "maxY": 250.5}, "class_id": 1, "box_caption": "small_D 0.055", "scores": {"class_score": 0.054962158203125}, "domain": "pixel"}, {"position": {"minX": 600.5, "minY": 270.25, "maxX": 607.5, "maxY": 281.75}, "class_id": 0, "box_caption": "medium_D 0.005", "scores": {"class_score": 0.0048065185546875}, "domain": "pixel"}, {"position": {"minX": 464.0, "minY": 142.625, "maxX": 554.0, "maxY": 210.125}, "class_id": 16, "box_caption": "moto_gp 0.005", "scores": {"class_score": 0.004547119140625}, "domain": "pixel"}, {"position": {"minX": 247.0, "minY": 216.25, "maxX": 270.0, "maxY": 224.25}, "class_id": 18, "box_caption": "F1 0.004", "scores": {"class_score": 0.004276275634765625}, "domain": "pixel"}, {"position": {"minX": 463.75, "minY": 142.625, "maxX": 554.0, "maxY": 210.375}, "class_id": 18, "box_caption": "F1 0.004", "scores": {"class_score": 0.003997802734375}, "domain": "pixel"}, {"position": {"minX": 31.8125, "minY": 196.75, "maxX": 52.5625, "maxY": 201.25}, "class_id": 0, "box_caption": "medium_D 0.003", "scores": {"class_score": 0.0033416748046875}, "domain": "pixel"}, {"position": {"minX": 495.0, "minY": 62.96875, "maxX": 515.5, "maxY": 73.875}, "class_id": 2, "box_caption": "large_D 0.003", "scores": {"class_score": 0.003185272216796875}, "domain": "pixel"}, {"position": {"minX": 354.0, "minY": 72.875, "maxX": 366.0, "maxY": 91.125}, "class_id": 2, "box_caption": "large_D 0.003", "scores": {"class_score": 0.003101348876953125}, "domain": "pixel"}, {"position": {"minX": 603.5, "minY": 139.25, "maxX": 622.5, "maxY": 151.0}, "class_id": 2, "box_caption": "large_D 0.003", "scores": {"class_score": 0.002994537353515625}, "domain": "pixel"}, {"position": {"minX": 323.25, "minY": 40.46875, "maxX": 327.75, "maxY": 44.53125}, "class_id": 0, "box_caption": "medium_D 0.003", "scores": {"class_score": 0.0029621124267578125}, "domain": "pixel"}, {"position": {"minX": 495.0, "minY": 63.0625, "maxX": 515.5, "maxY": 73.8125}, "class_id": 16, "box_caption": "moto_gp 0.003", "scores": {"class_score": 0.00286102294921875}, "domain": "pixel"}, {"position": {"minX": 354.25, "minY": 72.875, "maxX": 365.75, "maxY": 91.25}, "class_id": 16, "box_caption": "moto_gp 0.003", "scores": {"class_score": 0.0028533935546875}, "domain": "pixel"}, {"position": {"minX": 603.5, "minY": 139.375, "maxX": 622.5, "maxY": 151.125}, "class_id": 18, "box_caption": "F1 0.003", "scores": {"class_score": 0.002742767333984375}, "domain": "pixel"}, {"position": {"minX": 32.53125, "minY": 197.875, "maxX": 51.84375, "maxY": 200.375}, "class_id": 1, "box_caption": "small_D 0.003", "scores": {"class_score": 0.002658843994140625}, "domain": "pixel"}, {"position": {"minX": 51.3125, "minY": 277.0, "maxX": 72.4375, "maxY": 293.0}, "class_id": 0, "box_caption": "medium_D 0.003", "scores": {"class_score": 0.0025920867919921875}, "domain": "pixel"}, {"position": {"minX": 246.875, "minY": 216.25, "maxX": 270.25, "maxY": 224.25}, "class_id": 2, "box_caption": "large_D 0.003", "scores": {"class_score": 0.0025806427001953125}, "domain": "pixel"}, {"position": {"minX": 90.9375, "minY": 90.75, "maxX": 96.5625, "maxY": 102.625}, "class_id": 2, "box_caption": "large_D 0.003", "scores": {"class_score": 0.002506256103515625}, "domain": "pixel"}, {"position": {"minX": 379.0, "minY": 220.125, "maxX": 414.0, "maxY": 237.375}, "class_id": 0, "box_caption": "medium_D 0.002", "scores": {"class_score": 0.00244140625}, "domain": "pixel"}, {"position": {"minX": 495.0, "minY": 62.96875, "maxX": 515.5, "maxY": 73.875}, "class_id": 18, "box_caption": "F1 0.002", "scores": {"class_score": 0.002361297607421875}, "domain": "pixel"}, {"position": {"minX": 354.0, "minY": 72.875, "maxX": 366.0, "maxY": 91.125}, "class_id": 18, "box_caption": "F1 0.002", "scores": {"class_score": 0.0022449493408203125}, "domain": "pixel"}, {"position": {"minX": 600.0, "minY": 260.5, "maxX": 608.0, "maxY": 289.5}, "class_id": 16, "box_caption": "moto_gp 0.002", "scores": {"class_score": 0.002155303955078125}, "domain": "pixel"}, {"position": {"minX": 379.5, "minY": 220.25, "maxX": 414.0, "maxY": 237.5}, "class_id": 18, "box_caption": "F1 0.002", "scores": {"class_score": 0.0020084381103515625}, "domain": "pixel"}, {"position": {"minX": 323.0, "minY": 40.3125, "maxX": 328.0, "maxY": 44.6875}, "class_id": 2, "box_caption": "large_D 0.002", "scores": {"class_score": 0.0019931793212890625}, "domain": "pixel"}, {"position": {"minX": 246.625, "minY": 211.5, "maxX": 270.25, "maxY": 227.5}, "class_id": 0, "box_caption": "medium_D 0.002", "scores": {"class_score": 0.0019626617431640625}, "domain": "pixel"}, {"position": {"minX": 508.25, "minY": 132.625, "maxX": 522.5, "maxY": 135.875}, "class_id": 1, "box_caption": "small_D 0.002", "scores": {"class_score": 0.0019550323486328125}, "domain": "pixel"}, {"position": {"minX": 379.5, "minY": 220.25, "maxX": 414.0, "maxY": 237.5}, "class_id": 16, "box_caption": "moto_gp 0.002", "scores": {"class_score": 0.0018482208251953125}, "domain": "pixel"}, {"position": {"minX": 603.5, "minY": 139.375, "maxX": 622.5, "maxY": 151.125}, "class_id": 16, "box_caption": "moto_gp 0.002", "scores": {"class_score": 0.001842498779296875}, "domain": "pixel"}, {"position": {"minX": 51.1875, "minY": 276.75, "maxX": 72.5625, "maxY": 293.25}, "class_id": 16, "box_caption": "moto_gp 0.002", "scores": {"class_score": 0.0018167495727539062}, "domain": "pixel"}, {"position": {"minX": 51.09375, "minY": 277.0, "maxX": 72.625, "maxY": 293.5}, "class_id": 18, "box_caption": "F1 0.002", "scores": {"class_score": 0.001674652099609375}, "domain": "pixel"}, {"position": {"minX": 305.25, "minY": 253.125, "maxX": 331.75, "maxY": 257.0}, "class_id": 2, "box_caption": "large_D 0.002", "scores": {"class_score": 0.001617431640625}, "domain": "pixel"}, {"position": {"minX": 354.25, "minY": 72.875, "maxX": 365.75, "maxY": 91.25}, "class_id": 1, "box_caption": "small_D 0.002", "scores": {"class_score": 0.0015840530395507812}, "domain": "pixel"}, {"position": {"minX": 599.5, "minY": 260.25, "maxX": 608.5, "maxY": 289.75}, "class_id": 2, "box_caption": "large_D 0.002", "scores": {"class_score": 0.0015172958374023438}, "domain": "pixel"}, {"position": {"minX": 379.0, "minY": 220.125, "maxX": 414.0, "maxY": 237.375}, "class_id": 1, "box_caption": "small_D 0.001", "scores": {"class_score": 0.0014734268188476562}, "domain": "pixel"}, {"position": {"minX": 51.1875, "minY": 276.75, "maxX": 72.4375, "maxY": 293.25}, "class_id": 1, "box_caption": "small_D 0.001", "scores": {"class_score": 0.0013332366943359375}, "domain": "pixel"}, {"position": {"minX": 246.875, "minY": 216.25, "maxX": 270.25, "maxY": 224.25}, "class_id": 16, "box_caption": "moto_gp 0.001", "scores": {"class_score": 0.0013141632080078125}, "domain": "pixel"}, {"position": {"minX": 599.5, "minY": 260.25, "maxX": 608.5, "maxY": 289.75}, "class_id": 18, "box_caption": "F1 0.001", "scores": {"class_score": 0.0011920928955078125}, "domain": "pixel"}, {"position": {"minX": 246.625, "minY": 216.25, "maxX": 270.25, "maxY": 224.25}, "class_id": 1, "box_caption": "small_D 0.001", "scores": {"class_score": 0.0011339187622070312}, "domain": "pixel"}, {"position": {"minX": 311.0, "minY": 271.75, "maxX": 317.5, "maxY": 274.25}, "class_id": 1, "box_caption": "small_D 0.001", "scores": {"class_score": 0.0010547637939453125}, "domain": "pixel"}, {"position": {"minX": 508.25, "minY": 132.625, "maxX": 522.5, "maxY": 135.875}, "class_id": 2, "box_caption": "large_D 0.001", "scores": {"class_score": 0.0010433197021484375}, "domain": "pixel"}, {"position": {"minX": 90.875, "minY": 90.875, "maxX": 96.5, "maxY": 102.375}, "class_id": 1, "box_caption": "small_D 0.001", "scores": {"class_score": 0.00103759765625}, "domain": "pixel"}, {"position": {"minX": 305.25, "minY": 253.125, "maxX": 331.75, "maxY": 257.0}, "class_id": 1, "box_caption": "small_D 0.001", "scores": {"class_score": 0.0010271072387695312}, "domain": "pixel"}], "class_labels": {"0": "medium_D", "1": "small_D", "2": "large_D", "3": "pilot_standing", "4": "pilot_walking", "5": "pilot_racing", "6": "pilot_falling", "7": "pilot_sliding", "8": "pilot_injured", "9": "marshall", "10": "team_crew", "11": "spectator", "12": "helmet_full", "13": "helmet_open", "14": "helmet_fullX", "15": "safety_car", "16": "moto_gp", "17": "moto_x", "18": "F1", "19": "F2", "20": "F3", "21": "F4", "22": "FE", "23": "Indy", "24": "LMP", "25": "GT", "26": "wtcr", "27": "wrc", "28": "wrx", "29": "wtcr", "30": "rraid_Dakar", "31": "rraid_Baja", "32": "rraid_XE", "33": "nascar", "34": "sprint_car", "35": "green_flag", "36": "yellow_flag", "37": "red_flag", "38": "redyellow_F", "39": "blue_flag", "40": "black_flag", "41": "blackwhite_F", "42": "chequered_F", "43": "green_lights", "44": "red_lights", "45": "tarmac", "46": "gravel", "47": "brakD_S_50", "48": "brakD_S_100", "49": "brakD_S_150", "50": "apex", "51": "kerbs", "52": "lane", "53": "lines", "54": "start_fin_line", "55": "conc_wall", "56": "chocabs_wall", "57": "fencing", "58": "run_off", "59": "grass", "60": "cones", "61": "smock", "62": "oil", "63": "mud", "64": "sand", "65": "snow_ice", "66": "hole", "67": "jump", "68": "barrier_tape", "69": "wall", "70": "dune", "71": "tree", "72": "stone", "73": "barrier", "74": "house", "75": "car", "76": "lollipop"}}