{"box_data": [{"position": {"minX": 421.5, "minY": 185.75, "maxX": 488.0, "maxY": 240.5}, "class_id": 2, "box_caption": "large_D 0.968", "scores": {"class_score": 0.9677734375}, "domain": "pixel"}, {"position": {"minX": 27.84375, "minY": 90.125, "maxX": 73.75, "maxY": 141.875}, "class_id": 2, "box_caption": "large_D 0.964", "scores": {"class_score": 0.96435546875}, "domain": "pixel"}, {"position": {"minX": 16.625, "minY": 254.125, "maxX": 73.25, "maxY": 278.5}, "class_id": 2, "box_caption": "large_D 0.962", "scores": {"class_score": 0.96240234375}, "domain": "pixel"}, {"position": {"minX": 269.25, "minY": 69.5625, "maxX": 321.75, "maxY": 99.8125}, "class_id": 2, "box_caption": "large_D 0.959", "scores": {"class_score": 0.95947265625}, "domain": "pixel"}, {"position": {"minX": 501.75, "minY": 221.0, "maxX": 529.5, "maxY": 254.0}, "class_id": 2, "box_caption": "large_D 0.954", "scores": {"class_score": 0.9541015625}, "domain": "pixel"}, {"position": {"minX": 279.5, "minY": 243.625, "maxX": 312.5, "maxY": 259.75}, "class_id": 2, "box_caption": "large_D 0.952", "scores": {"class_score": 0.9521484375}, "domain": "pixel"}, {"position": {"minX": 577.5, "minY": 127.875, "maxX": 596.5, "maxY": 149.125}, "class_id": 0, "box_caption": "medium_D 0.950", "scores": {"class_score": 0.94970703125}, "domain": "pixel"}, {"position": {"minX": 543.5, "minY": 37.625, "maxX": 575.5, "maxY": 47.1875}, "class_id": 2, "box_caption": "large_D 0.941", "scores": {"class_score": 0.94091796875}, "domain": "pixel"}, {"position": {"minX": 633.5, "minY": 148.0, "maxX": 639.5, "maxY": 168.75}, "class_id": 0, "box_caption": "medium_D 0.936", "scores": {"class_score": 0.93603515625}, "domain": "pixel"}, {"position": {"minX": 438.5, "minY": 164.875, "maxX": 445.0, "maxY": 178.375}, "class_id": 0, "box_caption": "medium_D 0.928", "scores": {"class_score": 0.92822265625}, "domain": "pixel"}, {"position": {"minX": 408.0, "minY": 351.75, "maxX": 426.5, "maxY": 355.75}, "class_id": 0, "box_caption": "medium_D 0.920", "scores": {"class_score": 0.919921875}, "domain": "pixel"}, {"position": {"minX": 373.5, "minY": 223.0, "maxX": 381.5, "maxY": 236.0}, "class_id": 0, "box_caption": "medium_D 0.917", "scores": {"class_score": 0.9169921875}, "domain": "pixel"}, {"position": {"minX": 149.125, "minY": 214.0, "maxX": 155.625, "maxY": 236.0}, "class_id": 0, "box_caption": "medium_D 0.908", "scores": {"class_score": 0.90771484375}, "domain": "pixel"}, {"position": {"minX": 494.5, "minY": 274.25, "maxX": 513.5, "maxY": 279.25}, "class_id": 0, "box_caption": "medium_D 0.887", "scores": {"class_score": 0.88720703125}, "domain": "pixel"}, {"position": {"minX": 384.25, "minY": 131.0, "maxX": 390.75, "maxY": 141.5}, "class_id": 0, "box_caption": "medium_D 0.837", "scores": {"class_score": 0.83740234375}, "domain": "pixel"}, {"position": {"minX": 337.0, "minY": 211.5, "maxX": 349.0, "maxY": 214.0}, "class_id": 1, "box_caption": "small_D 0.052", "scores": {"class_score": 0.051727294921875}, "domain": "pixel"}, {"position": {"minX": 337.0, "minY": 211.5, "maxX": 349.0, "maxY": 214.0}, "class_id": 0, "box_caption": "medium_D 0.013", "scores": {"class_score": 0.01268768310546875}, "domain": "pixel"}, {"position": {"minX": 109.75, "minY": 216.75, "maxX": 127.375, "maxY": 219.5}, "class_id": 1, "box_caption": "small_D 0.007", "scores": {"class_score": 0.007068634033203125}, "domain": "pixel"}, {"position": {"minX": 185.0, "minY": 225.5, "maxX": 193.5, "maxY": 227.75}, "class_id": 1, "box_caption": "small_D 0.007", "scores": {"class_score": 0.00681304931640625}, "domain": "pixel"}, {"position": {"minX": 16.65625, "minY": 254.375, "maxX": 73.25, "maxY": 278.75}, "class_id": 18, "box_caption": "F1 0.005", "scores": {"class_score": 0.004947662353515625}, "domain": "pixel"}, {"position": {"minX": 269.25, "minY": 69.625, "maxX": 321.75, "maxY": 99.75}, "class_id": 18, "box_caption": "F1 0.005", "scores": {"class_score": 0.004573822021484375}, "domain": "pixel"}, {"position": {"minX": 80.125, "minY": 198.5, "maxX": 91.0, "maxY": 201.25}, "class_id": 1, "box_caption": "small_D 0.004", "scores": {"class_score": 0.00437164306640625}, "domain": "pixel"}, {"position": {"minX": 421.5, "minY": 185.5, "maxX": 488.0, "maxY": 241.0}, "class_id": 18, "box_caption": "F1 0.004", "scores": {"class_score": 0.00403594970703125}, "domain": "pixel"}, {"position": {"minX": 421.5, "minY": 185.5, "maxX": 488.0, "maxY": 241.0}, "class_id": 16, "box_caption": "moto_gp 0.004", "scores": {"class_score": 0.004016876220703125}, "domain": "pixel"}, {"position": {"minX": 27.453125, "minY": 90.1875, "maxX": 73.8125, "maxY": 142.25}, "class_id": 16, "box_caption": "moto_gp 0.004", "scores": {"class_score": 0.003971099853515625}, "domain": "pixel"}, {"position": {"minX": 185.0, "minY": 225.5, "maxX": 193.5, "maxY": 227.75}, "class_id": 0, "box_caption": "medium_D 0.004", "scores": {"class_score": 0.0038299560546875}, "domain": "pixel"}, {"position": {"minX": 543.5, "minY": 37.625, "maxX": 575.5, "maxY": 47.1875}, "class_id": 1, "box_caption": "small_D 0.004", "scores": {"class_score": 0.0036773681640625}, "domain": "pixel"}, {"position": {"minX": 27.453125, "minY": 90.1875, "maxX": 73.8125, "maxY": 142.25}, "class_id": 18, "box_caption": "F1 0.004", "scores": {"class_score": 0.0035877227783203125}, "domain": "pixel"}, {"position": {"minX": 402.5, "minY": 183.25, "maxX": 512.0, "maxY": 243.0}, "class_id": 2, "box_caption": "large_D 0.004", "scores": {"class_score": 0.0035419464111328125}, "domain": "pixel"}, {"position": {"minX": 577.5, "minY": 128.0, "maxX": 596.5, "maxY": 149.0}, "class_id": 16, "box_caption": "moto_gp 0.003", "scores": {"class_score": 0.00334930419921875}, "domain": "pixel"}, {"position": {"minX": 306.75, "minY": 207.75, "maxX": 312.25, "maxY": 211.0}, "class_id": 1, "box_caption": "small_D 0.003", "scores": {"class_score": 0.003215789794921875}, "domain": "pixel"}, {"position": {"minX": 577.5, "minY": 127.875, "maxX": 596.5, "maxY": 149.125}, "class_id": 2, "box_caption": "large_D 0.003", "scores": {"class_score": 0.0032100677490234375}, "domain": "pixel"}, {"position": {"minX": 543.0, "minY": 34.125, "maxX": 576.0, "maxY": 49.625}, "class_id": 2, "box_caption": "large_D 0.003", "scores": {"class_score": 0.0030956268310546875}, "domain": "pixel"}, {"position": {"minX": 543.5, "minY": 37.65625, "maxX": 575.5, "maxY": 47.09375}, "class_id": 0, "box_caption": "medium_D 0.003", "scores": {"class_score": 0.0030670166015625}, "domain": "pixel"}, {"position": {"minX": -9.8125, "minY": 86.4375, "maxX": 109.5625, "maxY": 145.75}, "class_id": 2, "box_caption": "large_D 0.003", "scores": {"class_score": 0.0030059814453125}, "domain": "pixel"}, {"position": {"minX": 436.0, "minY": 234.625, "maxX": 446.5, "maxY": 238.625}, "class_id": 1, "box_caption": "small_D 0.003", "scores": {"class_score": 0.002716064453125}, "domain": "pixel"}, {"position": {"minX": 278.75, "minY": 243.125, "maxX": 312.75, "maxY": 259.75}, "class_id": 0, "box_caption": "medium_D 0.003", "scores": {"class_score": 0.002716064453125}, "domain": "pixel"}, {"position": {"minX": 335.25, "minY": 210.5, "maxX": 348.25, "maxY": 212.75}, "class_id": 1, "box_caption": "small_D 0.003", "scores": {"class_score": 0.0026340484619140625}, "domain": "pixel"}, {"position": {"minX": 577.5, "minY": 128.0, "maxX": 596.5, "maxY": 149.0}, "class_id": 18, "box_caption": "F1 0.003", "scores": {"class_score": 0.0026226043701171875}, "domain": "pixel"}, {"position": {"minX": 16.5625, "minY": 254.25, "maxX": 73.1875, "maxY": 278.75}, "class_id": 16, "box_caption": "moto_gp 0.003", "scores": {"class_score": 0.0026111602783203125}, "domain": "pixel"}, {"position": {"minX": 269.25, "minY": 69.8125, "maxX": 321.75, "maxY": 99.6875}, "class_id": 16, "box_caption": "moto_gp 0.002", "scores": {"class_score": 0.002391815185546875}, "domain": "pixel"}, {"position": {"minX": 501.75, "minY": 221.125, "maxX": 529.5, "maxY": 254.125}, "class_id": 18, "box_caption": "F1 0.002", "scores": {"class_score": 0.0022869110107421875}, "domain": "pixel"}, {"position": {"minX": 543.5, "minY": 37.65625, "maxX": 575.5, "maxY": 47.09375}, "class_id": 18, "box_caption": "F1 0.002", "scores": {"class_score": 0.002262115478515625}, "domain": "pixel"}, {"position": {"minX": 438.5, "minY": 164.875, "maxX": 445.0, "maxY": 178.375}, "class_id": 2, "box_caption": "large_D 0.002", "scores": {"class_score": 0.0022220611572265625}, "domain": "pixel"}, {"position": {"minX": 373.75, "minY": 223.125, "maxX": 381.75, "maxY": 235.875}, "class_id": 2, "box_caption": "large_D 0.002", "scores": {"class_score": 0.002162933349609375}, "domain": "pixel"}, {"position": {"minX": 149.25, "minY": 219.625, "maxX": 155.5, "maxY": 232.125}, "class_id": 0, "box_caption": "medium_D 0.002", "scores": {"class_score": 0.0019588470458984375}, "domain": "pixel"}, {"position": {"minX": 501.75, "minY": 220.75, "maxX": 529.5, "maxY": 254.25}, "class_id": 16, "box_caption": "moto_gp 0.002", "scores": {"class_score": 0.0018377304077148438}, "domain": "pixel"}, {"position": {"minX": 109.75, "minY": 216.75, "maxX": 127.375, "maxY": 219.5}, "class_id": 0, "box_caption": "medium_D 0.002", "scores": {"class_score": 0.0018243789672851562}, "domain": "pixel"}, {"position": {"minX": 279.25, "minY": 243.375, "maxX": 312.25, "maxY": 259.75}, "class_id": 16, "box_caption": "moto_gp 0.002", "scores": {"class_score": 0.001811981201171875}, "domain": "pixel"}, {"position": {"minX": 578.0, "minY": 132.5, "maxX": 596.0, "maxY": 144.75}, "class_id": 0, "box_caption": "medium_D 0.002", "scores": {"class_score": 0.0017309188842773438}, "domain": "pixel"}, {"position": {"minX": 269.75, "minY": 166.125, "maxX": 275.25, "maxY": 169.875}, "class_id": 1, "box_caption": "small_D 0.002", "scores": {"class_score": 0.0017118453979492188}, "domain": "pixel"}, {"position": {"minX": 279.5, "minY": 243.625, "maxX": 312.5, "maxY": 259.75}, "class_id": 18, "box_caption": "F1 0.002", "scores": {"class_score": 0.0017108917236328125}, "domain": "pixel"}, {"position": {"minX": 440.0, "minY": 235.25, "maxX": 447.5, "maxY": 238.25}, "class_id": 1, "box_caption": "small_D 0.002", "scores": {"class_score": 0.0016832351684570312}, "domain": "pixel"}, {"position": {"minX": -19.8125, "minY": 246.5, "maxX": 111.6875, "maxY": 283.0}, "class_id": 2, "box_caption": "large_D 0.002", "scores": {"class_score": 0.0016565322875976562}, "domain": "pixel"}, {"position": {"minX": 634.0, "minY": 151.5, "maxX": 640.0, "maxY": 164.25}, "class_id": 0, "box_caption": "medium_D 0.002", "scores": {"class_score": 0.001575469970703125}, "domain": "pixel"}, {"position": {"minX": 68.375, "minY": 200.125, "maxX": 73.375, "maxY": 202.875}, "class_id": 1, "box_caption": "small_D 0.002", "scores": {"class_score": 0.00152587890625}, "domain": "pixel"}, {"position": {"minX": 232.875, "minY": 62.34375, "maxX": 364.5, "maxY": 105.125}, "class_id": 2, "box_caption": "large_D 0.001", "scores": {"class_score": 0.0014867782592773438}, "domain": "pixel"}, {"position": {"minX": 384.5, "minY": 131.0, "maxX": 390.5, "maxY": 142.25}, "class_id": 1, "box_caption": "small_D 0.001", "scores": {"class_score": 0.0013704299926757812}, "domain": "pixel"}, {"position": {"minX": 501.25, "minY": 221.0, "maxX": 529.0, "maxY": 254.0}, "class_id": 0, "box_caption": "medium_D 0.001", "scores": {"class_score": 0.0013580322265625}, "domain": "pixel"}, {"position": {"minX": 269.25, "minY": 165.75, "maxX": 274.25, "maxY": 169.25}, "class_id": 1, "box_caption": "small_D 0.001", "scores": {"class_score": 0.001308441162109375}, "domain": "pixel"}, {"position": {"minX": 149.125, "minY": 213.875, "maxX": 155.625, "maxY": 235.875}, "class_id": 1, "box_caption": "small_D 0.001", "scores": {"class_score": 0.0012493133544921875}, "domain": "pixel"}, {"position": {"minX": 540.5, "minY": 28.0, "maxX": 578.5, "maxY": 58.0625}, "class_id": 2, "box_caption": "large_D 0.001", "scores": {"class_score": 0.0012235641479492188}, "domain": "pixel"}, {"position": {"minX": 149.125, "minY": 213.875, "maxX": 155.625, "maxY": 235.875}, "class_id": 2, "box_caption": "large_D 0.001", "scores": {"class_score": 0.0012102127075195312}, "domain": "pixel"}, {"position": {"minX": 384.25, "minY": 130.875, "maxX": 390.75, "maxY": 142.375}, "class_id": 2, "box_caption": "large_D 0.001", "scores": {"class_score": 0.00116729736328125}, "domain": "pixel"}, {"position": {"minX": 633.5, "minY": 148.25, "maxX": 639.5, "maxY": 169.0}, "class_id": 2, "box_caption": "large_D 0.001", "scores": {"class_score": 0.0011653900146484375}, "domain": "pixel"}, {"position": {"minX": 494.5, "minY": 274.25, "maxX": 513.5, "maxY": 279.25}, "class_id": 16, "box_caption": "moto_gp 0.001", "scores": {"class_score": 0.0011587142944335938}, "domain": "pixel"}, {"position": {"minX": 68.0, "minY": 199.5, "maxX": 74.875, "maxY": 202.0}, "class_id": 1, "box_caption": "small_D 0.001", "scores": {"class_score": 0.0011425018310546875}, "domain": "pixel"}, {"position": {"minX": 269.25, "minY": 69.625, "maxX": 321.75, "maxY": 99.75}, "class_id": 0, "box_caption": "medium_D 0.001", "scores": {"class_score": 0.00113677978515625}, "domain": "pixel"}, {"position": {"minX": 16.546875, "minY": 254.0, "maxX": 73.3125, "maxY": 278.5}, "class_id": 0, "box_caption": "medium_D 0.001", "scores": {"class_score": 0.0011301040649414062}, "domain": "pixel"}, {"position": {"minX": 440.5, "minY": 234.25, "maxX": 451.5, "maxY": 238.75}, "class_id": 1, "box_caption": "small_D 0.001", "scores": {"class_score": 0.0010862350463867188}, "domain": "pixel"}, {"position": {"minX": 543.5, "minY": 37.71875, "maxX": 575.5, "maxY": 47.21875}, "class_id": 16, "box_caption": "moto_gp 0.001", "scores": {"class_score": 0.0010833740234375}, "domain": "pixel"}, {"position": {"minX": 149.125, "minY": 213.875, "maxX": 155.625, "maxY": 235.875}, "class_id": 16, "box_caption": "moto_gp 0.001", "scores": {"class_score": 0.0010766983032226562}, "domain": "pixel"}, {"position": {"minX": 633.5, "minY": 148.0, "maxX": 639.5, "maxY": 168.75}, "class_id": 16, "box_caption": "moto_gp 0.001", "scores": {"class_score": 0.0010461807250976562}, "domain": "pixel"}, {"position": {"minX": 27.46875, "minY": 89.4375, "maxX": 73.75, "maxY": 141.625}, "class_id": 0, "box_caption": "medium_D 0.001", "scores": {"class_score": 0.0010404586791992188}, "domain": "pixel"}, {"position": {"minX": 438.5, "minY": 164.875, "maxX": 445.0, "maxY": 178.375}, "class_id": 18, "box_caption": "F1 0.001", "scores": {"class_score": 0.0010232925415039062}, "domain": "pixel"}, {"position": {"minX": 577.5, "minY": 128.0, "maxX": 596.5, "maxY": 149.0}, "class_id": 1, "box_caption": "small_D 0.001", "scores": {"class_score": 0.0010128021240234375}, "domain": "pixel"}, {"position": {"minX": 421.5, "minY": 185.75, "maxX": 488.0, "maxY": 240.5}, "class_id": 0, "box_caption": "medium_D 0.001", "scores": {"class_score": 0.0010023117065429688}, "domain": "pixel"}], "class_labels": {"0": "medium_D", "1": "small_D", "2": "large_D", "3": "pilot_standing", "4": "pilot_walking", "5": "pilot_racing", "6": "pilot_falling", "7": "pilot_sliding", "8": "pilot_injured", "9": "marshall", "10": "team_crew", "11": "spectator", "12": "helmet_full", "13": "helmet_open", "14": "helmet_fullX", "15": "safety_car", "16": "moto_gp", "17": "moto_x", "18": "F1", "19": "F2", "20": "F3", "21": "F4", "22": "FE", "23": "Indy", "24": "LMP", "25": "GT", "26": "wtcr", "27": "wrc", "28": "wrx", "29": "wtcr", "30": "rraid_Dakar", "31": "rraid_Baja", "32": "rraid_XE", "33": "nascar", "34": "sprint_car", "35": "green_flag", "36": "yellow_flag", "37": "red_flag", "38": "redyellow_F", "39": "blue_flag", "40": "black_flag", "41": "blackwhite_F", "42": "chequered_F", "43": "green_lights", "44": "red_lights", "45": "tarmac", "46": "gravel", "47": "brakD_S_50", "48": "brakD_S_100", "49": "brakD_S_150", "50": "apex", "51": "kerbs", "52": "lane", "53": "lines", "54": "start_fin_line", "55": "conc_wall", "56": "chocabs_wall", "57": "fencing", "58": "run_off", "59": "grass", "60": "cones", "61": "smock", "62": "oil", "63": "mud", "64": "sand", "65": "snow_ice", "66": "hole", "67": "jump", "68": "barrier_tape", "69": "wall", "70": "dune", "71": "tree", "72": "stone", "73": "barrier", "74": "house", "75": "car", "76": "lollipop"}}