{"box_data": [{"position": {"minX": 420.5, "minY": 185.875, "maxX": 487.5, "maxY": 239.625}, "class_id": 2, "box_caption": "large_D 0.955", "scores": {"class_score": 0.95458984375}, "domain": "pixel"}, {"position": {"minX": 269.0, "minY": 69.5625, "maxX": 322.0, "maxY": 99.8125}, "class_id": 2, "box_caption": "large_D 0.953", "scores": {"class_score": 0.953125}, "domain": "pixel"}, {"position": {"minX": 27.46875, "minY": 90.125, "maxX": 74.0, "maxY": 142.375}, "class_id": 2, "box_caption": "large_D 0.948", "scores": {"class_score": 0.94775390625}, "domain": "pixel"}, {"position": {"minX": 501.75, "minY": 221.0, "maxX": 529.0, "maxY": 254.25}, "class_id": 2, "box_caption": "large_D 0.947", "scores": {"class_score": 0.94677734375}, "domain": "pixel"}, {"position": {"minX": 543.5, "minY": 37.65625, "maxX": 575.5, "maxY": 47.15625}, "class_id": 2, "box_caption": "large_D 0.941", "scores": {"class_score": 0.94091796875}, "domain": "pixel"}, {"position": {"minX": 279.25, "minY": 243.625, "maxX": 312.75, "maxY": 259.75}, "class_id": 2, "box_caption": "large_D 0.938", "scores": {"class_score": 0.93798828125}, "domain": "pixel"}, {"position": {"minX": 16.25, "minY": 254.375, "maxX": 73.875, "maxY": 278.75}, "class_id": 2, "box_caption": "large_D 0.937", "scores": {"class_score": 0.9365234375}, "domain": "pixel"}, {"position": {"minX": 577.5, "minY": 128.0, "maxX": 596.5, "maxY": 148.75}, "class_id": 0, "box_caption": "medium_D 0.926", "scores": {"class_score": 0.92578125}, "domain": "pixel"}, {"position": {"minX": 407.5, "minY": 351.5, "maxX": 426.5, "maxY": 356.0}, "class_id": 0, "box_caption": "medium_D 0.905", "scores": {"class_score": 0.90478515625}, "domain": "pixel"}, {"position": {"minX": 149.125, "minY": 214.0, "maxX": 155.875, "maxY": 235.75}, "class_id": 0, "box_caption": "medium_D 0.904", "scores": {"class_score": 0.904296875}, "domain": "pixel"}, {"position": {"minX": 634.0, "minY": 148.0, "maxX": 640.0, "maxY": 169.0}, "class_id": 0, "box_caption": "medium_D 0.885", "scores": {"class_score": 0.88525390625}, "domain": "pixel"}, {"position": {"minX": 373.75, "minY": 223.25, "maxX": 381.75, "maxY": 236.0}, "class_id": 0, "box_caption": "medium_D 0.882", "scores": {"class_score": 0.88232421875}, "domain": "pixel"}, {"position": {"minX": 438.5, "minY": 165.125, "maxX": 445.0, "maxY": 178.375}, "class_id": 0, "box_caption": "medium_D 0.875", "scores": {"class_score": 0.87548828125}, "domain": "pixel"}, {"position": {"minX": 494.5, "minY": 274.25, "maxX": 513.5, "maxY": 279.25}, "class_id": 0, "box_caption": "medium_D 0.870", "scores": {"class_score": 0.8701171875}, "domain": "pixel"}, {"position": {"minX": 384.25, "minY": 130.75, "maxX": 390.25, "maxY": 141.75}, "class_id": 0, "box_caption": "medium_D 0.761", "scores": {"class_score": 0.76123046875}, "domain": "pixel"}, {"position": {"minX": 338.25, "minY": 211.5, "maxX": 349.25, "maxY": 214.25}, "class_id": 1, "box_caption": "small_D 0.008", "scores": {"class_score": 0.007633209228515625}, "domain": "pixel"}, {"position": {"minX": 16.796875, "minY": 253.625, "maxX": 74.3125, "maxY": 278.5}, "class_id": 18, "box_caption": "F1 0.006", "scores": {"class_score": 0.00627899169921875}, "domain": "pixel"}, {"position": {"minX": 80.4375, "minY": 198.375, "maxX": 90.6875, "maxY": 201.375}, "class_id": 1, "box_caption": "small_D 0.005", "scores": {"class_score": 0.0054931640625}, "domain": "pixel"}, {"position": {"minX": 269.5, "minY": 69.5625, "maxX": 321.5, "maxY": 99.6875}, "class_id": 18, "box_caption": "F1 0.005", "scores": {"class_score": 0.005115509033203125}, "domain": "pixel"}, {"position": {"minX": 578.0, "minY": 128.125, "maxX": 597.0, "maxY": 148.625}, "class_id": 16, "box_caption": "moto_gp 0.005", "scores": {"class_score": 0.00482177734375}, "domain": "pixel"}, {"position": {"minX": 578.0, "minY": 127.875, "maxX": 597.0, "maxY": 148.625}, "class_id": 2, "box_caption": "large_D 0.005", "scores": {"class_score": 0.0047149658203125}, "domain": "pixel"}, {"position": {"minX": 27.546875, "minY": 90.25, "maxX": 73.8125, "maxY": 142.5}, "class_id": 18, "box_caption": "F1 0.005", "scores": {"class_score": 0.00470733642578125}, "domain": "pixel"}, {"position": {"minX": 27.546875, "minY": 90.25, "maxX": 73.8125, "maxY": 142.5}, "class_id": 16, "box_caption": "moto_gp 0.005", "scores": {"class_score": 0.004619598388671875}, "domain": "pixel"}, {"position": {"minX": 269.75, "minY": 166.375, "maxX": 275.75, "maxY": 170.125}, "class_id": 1, "box_caption": "small_D 0.004", "scores": {"class_score": 0.004428863525390625}, "domain": "pixel"}, {"position": {"minX": 421.5, "minY": 186.125, "maxX": 488.0, "maxY": 239.875}, "class_id": 16, "box_caption": "moto_gp 0.004", "scores": {"class_score": 0.004413604736328125}, "domain": "pixel"}, {"position": {"minX": 421.5, "minY": 185.625, "maxX": 488.0, "maxY": 240.125}, "class_id": 18, "box_caption": "F1 0.004", "scores": {"class_score": 0.00440216064453125}, "domain": "pixel"}, {"position": {"minX": 543.5, "minY": 37.65625, "maxX": 575.5, "maxY": 46.96875}, "class_id": 0, "box_caption": "medium_D 0.004", "scores": {"class_score": 0.004302978515625}, "domain": "pixel"}, {"position": {"minX": 578.0, "minY": 128.125, "maxX": 597.0, "maxY": 148.625}, "class_id": 18, "box_caption": "F1 0.004", "scores": {"class_score": 0.00414276123046875}, "domain": "pixel"}, {"position": {"minX": 543.5, "minY": 37.65625, "maxX": 575.5, "maxY": 47.15625}, "class_id": 1, "box_caption": "small_D 0.004", "scores": {"class_score": 0.004131317138671875}, "domain": "pixel"}, {"position": {"minX": 634.0, "minY": 151.5, "maxX": 640.0, "maxY": 163.75}, "class_id": 0, "box_caption": "medium_D 0.004", "scores": {"class_score": 0.003925323486328125}, "domain": "pixel"}, {"position": {"minX": 185.125, "minY": 225.375, "maxX": 193.375, "maxY": 227.625}, "class_id": 1, "box_caption": "small_D 0.004", "scores": {"class_score": 0.0037136077880859375}, "domain": "pixel"}, {"position": {"minX": 16.375, "minY": 254.25, "maxX": 73.625, "maxY": 278.25}, "class_id": 16, "box_caption": "moto_gp 0.003", "scores": {"class_score": 0.0034580230712890625}, "domain": "pixel"}, {"position": {"minX": -15.3125, "minY": 84.5625, "maxX": 114.8125, "maxY": 147.25}, "class_id": 2, "box_caption": "large_D 0.003", "scores": {"class_score": 0.0031337738037109375}, "domain": "pixel"}, {"position": {"minX": 269.5, "minY": 69.5625, "maxX": 321.5, "maxY": 99.6875}, "class_id": 16, "box_caption": "moto_gp 0.003", "scores": {"class_score": 0.003108978271484375}, "domain": "pixel"}, {"position": {"minX": 394.5, "minY": 181.25, "maxX": 519.5, "maxY": 244.0}, "class_id": 2, "box_caption": "large_D 0.003", "scores": {"class_score": 0.0031070709228515625}, "domain": "pixel"}, {"position": {"minX": 501.75, "minY": 221.5, "maxX": 529.0, "maxY": 254.0}, "class_id": 18, "box_caption": "F1 0.003", "scores": {"class_score": 0.003101348876953125}, "domain": "pixel"}, {"position": {"minX": 185.125, "minY": 225.375, "maxX": 193.375, "maxY": 227.625}, "class_id": 0, "box_caption": "medium_D 0.003", "scores": {"class_score": 0.0029582977294921875}, "domain": "pixel"}, {"position": {"minX": 543.5, "minY": 37.65625, "maxX": 575.5, "maxY": 47.15625}, "class_id": 18, "box_caption": "F1 0.003", "scores": {"class_score": 0.0029354095458984375}, "domain": "pixel"}, {"position": {"minX": 373.5, "minY": 223.25, "maxX": 381.5, "maxY": 236.0}, "class_id": 2, "box_caption": "large_D 0.003", "scores": {"class_score": 0.002925872802734375}, "domain": "pixel"}, {"position": {"minX": 440.0, "minY": 235.375, "maxX": 448.0, "maxY": 238.375}, "class_id": 1, "box_caption": "small_D 0.003", "scores": {"class_score": 0.0026988983154296875}, "domain": "pixel"}, {"position": {"minX": 501.75, "minY": 221.0, "maxX": 529.0, "maxY": 254.25}, "class_id": 16, "box_caption": "moto_gp 0.003", "scores": {"class_score": 0.0025691986083984375}, "domain": "pixel"}, {"position": {"minX": 278.75, "minY": 243.125, "maxX": 312.75, "maxY": 260.0}, "class_id": 0, "box_caption": "medium_D 0.003", "scores": {"class_score": 0.0025634765625}, "domain": "pixel"}, {"position": {"minX": 149.625, "minY": 219.875, "maxX": 155.375, "maxY": 232.625}, "class_id": 0, "box_caption": "medium_D 0.003", "scores": {"class_score": 0.002521514892578125}, "domain": "pixel"}, {"position": {"minX": 542.5, "minY": 32.65625, "maxX": 576.5, "maxY": 50.71875}, "class_id": 2, "box_caption": "large_D 0.003", "scores": {"class_score": 0.0025196075439453125}, "domain": "pixel"}, {"position": {"minX": 438.5, "minY": 164.875, "maxX": 445.0, "maxY": 178.375}, "class_id": 2, "box_caption": "large_D 0.002", "scores": {"class_score": 0.0023632049560546875}, "domain": "pixel"}, {"position": {"minX": 109.375, "minY": 217.0, "maxX": 121.5, "maxY": 219.75}, "class_id": 1, "box_caption": "small_D 0.002", "scores": {"class_score": 0.002353668212890625}, "domain": "pixel"}, {"position": {"minX": 633.5, "minY": 147.375, "maxX": 640.5, "maxY": 169.125}, "class_id": 2, "box_caption": "large_D 0.002", "scores": {"class_score": 0.0023059844970703125}, "domain": "pixel"}, {"position": {"minX": 279.25, "minY": 243.5, "maxX": 312.75, "maxY": 260.0}, "class_id": 16, "box_caption": "moto_gp 0.002", "scores": {"class_score": 0.00225830078125}, "domain": "pixel"}, {"position": {"minX": 279.0, "minY": 243.75, "maxX": 312.5, "maxY": 259.75}, "class_id": 18, "box_caption": "F1 0.002", "scores": {"class_score": 0.00214385986328125}, "domain": "pixel"}, {"position": {"minX": 338.25, "minY": 211.5, "maxX": 349.25, "maxY": 214.25}, "class_id": 0, "box_caption": "medium_D 0.002", "scores": {"class_score": 0.002132415771484375}, "domain": "pixel"}, {"position": {"minX": 149.125, "minY": 213.875, "maxX": 155.625, "maxY": 235.875}, "class_id": 2, "box_caption": "large_D 0.002", "scores": {"class_score": 0.002117156982421875}, "domain": "pixel"}, {"position": {"minX": 578.5, "minY": 132.625, "maxX": 595.5, "maxY": 144.875}, "class_id": 0, "box_caption": "medium_D 0.002", "scores": {"class_score": 0.0020923614501953125}, "domain": "pixel"}, {"position": {"minX": 437.0, "minY": 233.625, "maxX": 449.0, "maxY": 238.875}, "class_id": 1, "box_caption": "small_D 0.002", "scores": {"class_score": 0.0020885467529296875}, "domain": "pixel"}, {"position": {"minX": 494.5, "minY": 274.0, "maxX": 513.5, "maxY": 279.0}, "class_id": 1, "box_caption": "small_D 0.002", "scores": {"class_score": 0.0020771026611328125}, "domain": "pixel"}, {"position": {"minX": 494.5, "minY": 274.25, "maxX": 513.5, "maxY": 279.25}, "class_id": 16, "box_caption": "moto_gp 0.002", "scores": {"class_score": 0.0020580291748046875}, "domain": "pixel"}, {"position": {"minX": 502.0, "minY": 221.25, "maxX": 529.0, "maxY": 254.0}, "class_id": 0, "box_caption": "medium_D 0.002", "scores": {"class_score": 0.00200653076171875}, "domain": "pixel"}, {"position": {"minX": 384.75, "minY": 130.5, "maxX": 390.25, "maxY": 141.0}, "class_id": 1, "box_caption": "small_D 0.002", "scores": {"class_score": 0.0018033981323242188}, "domain": "pixel"}, {"position": {"minX": 634.0, "minY": 148.0, "maxX": 640.0, "maxY": 169.0}, "class_id": 1, "box_caption": "small_D 0.002", "scores": {"class_score": 0.0017871856689453125}, "domain": "pixel"}, {"position": {"minX": 269.25, "minY": 69.5625, "maxX": 321.75, "maxY": 99.9375}, "class_id": 0, "box_caption": "medium_D 0.002", "scores": {"class_score": 0.0017452239990234375}, "domain": "pixel"}, {"position": {"minX": 109.375, "minY": 217.0, "maxX": 121.5, "maxY": 219.75}, "class_id": 0, "box_caption": "medium_D 0.002", "scores": {"class_score": 0.0017261505126953125}, "domain": "pixel"}, {"position": {"minX": 577.5, "minY": 128.25, "maxX": 596.5, "maxY": 148.75}, "class_id": 1, "box_caption": "small_D 0.002", "scores": {"class_score": 0.001689910888671875}, "domain": "pixel"}, {"position": {"minX": 16.375, "minY": 254.0, "maxX": 73.6875, "maxY": 278.5}, "class_id": 0, "box_caption": "medium_D 0.002", "scores": {"class_score": 0.0016851425170898438}, "domain": "pixel"}, {"position": {"minX": 421.0, "minY": 185.75, "maxX": 488.0, "maxY": 240.0}, "class_id": 0, "box_caption": "medium_D 0.002", "scores": {"class_score": 0.0016574859619140625}, "domain": "pixel"}, {"position": {"minX": 225.75, "minY": 61.0625, "maxX": 342.75, "maxY": 105.3125}, "class_id": 2, "box_caption": "large_D 0.002", "scores": {"class_score": 0.0015916824340820312}, "domain": "pixel"}, {"position": {"minX": 27.484375, "minY": 89.6875, "maxX": 73.5, "maxY": 141.25}, "class_id": 0, "box_caption": "medium_D 0.002", "scores": {"class_score": 0.00157928466796875}, "domain": "pixel"}, {"position": {"minX": 438.5, "minY": 165.125, "maxX": 445.0, "maxY": 178.375}, "class_id": 18, "box_caption": "F1 0.002", "scores": {"class_score": 0.0015239715576171875}, "domain": "pixel"}, {"position": {"minX": 543.5, "minY": 37.71875, "maxX": 575.5, "maxY": 46.96875}, "class_id": 16, "box_caption": "moto_gp 0.002", "scores": {"class_score": 0.0015115737915039062}, "domain": "pixel"}, {"position": {"minX": 634.0, "minY": 147.875, "maxX": 640.0, "maxY": 168.875}, "class_id": 18, "box_caption": "F1 0.002", "scores": {"class_score": 0.0015001296997070312}, "domain": "pixel"}, {"position": {"minX": 502.0, "minY": 221.25, "maxX": 529.0, "maxY": 254.0}, "class_id": 40, "box_caption": "black_flag 0.001", "scores": {"class_score": 0.0014524459838867188}, "domain": "pixel"}, {"position": {"minX": 279.0, "minY": 243.75, "maxX": 312.5, "maxY": 259.75}, "class_id": 1, "box_caption": "small_D 0.001", "scores": {"class_score": 0.0014514923095703125}, "domain": "pixel"}, {"position": {"minX": 502.0, "minY": 221.25, "maxX": 529.0, "maxY": 254.0}, "class_id": 71, "box_caption": "tree 0.001", "scores": {"class_score": 0.0014362335205078125}, "domain": "pixel"}, {"position": {"minX": -21.375, "minY": 245.25, "maxX": 113.5, "maxY": 286.75}, "class_id": 2, "box_caption": "large_D 0.001", "scores": {"class_score": 0.0014333724975585938}, "domain": "pixel"}, {"position": {"minX": 634.0, "minY": 148.0, "maxX": 640.0, "maxY": 169.0}, "class_id": 16, "box_caption": "moto_gp 0.001", "scores": {"class_score": 0.0014324188232421875}, "domain": "pixel"}, {"position": {"minX": 502.0, "minY": 221.25, "maxX": 529.0, "maxY": 254.0}, "class_id": 61, "box_caption": "smock 0.001", "scores": {"class_score": 0.001430511474609375}, "domain": "pixel"}, {"position": {"minX": 502.0, "minY": 221.25, "maxX": 529.0, "maxY": 254.0}, "class_id": 29, "box_caption": "wtcr 0.001", "scores": {"class_score": 0.0014142990112304688}, "domain": "pixel"}, {"position": {"minX": 502.0, "minY": 221.25, "maxX": 529.0, "maxY": 254.0}, "class_id": 38, "box_caption": "redyellow_F 0.001", "scores": {"class_score": 0.0014142990112304688}, "domain": "pixel"}, {"position": {"minX": 502.0, "minY": 221.25, "maxX": 529.0, "maxY": 254.0}, "class_id": 64, "box_caption": "sand 0.001", "scores": {"class_score": 0.0014142990112304688}, "domain": "pixel"}, {"position": {"minX": 438.5, "minY": 164.875, "maxX": 445.0, "maxY": 178.375}, "class_id": 1, "box_caption": "small_D 0.001", "scores": {"class_score": 0.0014123916625976562}, "domain": "pixel"}, {"position": {"minX": 502.0, "minY": 221.25, "maxX": 529.0, "maxY": 254.0}, "class_id": 14, "box_caption": "helmet_fullX 0.001", "scores": {"class_score": 0.0014085769653320312}, "domain": "pixel"}, {"position": {"minX": 502.0, "minY": 221.25, "maxX": 529.0, "maxY": 254.0}, "class_id": 33, "box_caption": "nascar 0.001", "scores": {"class_score": 0.0014085769653320312}, "domain": "pixel"}, {"position": {"minX": 502.0, "minY": 221.25, "maxX": 529.0, "maxY": 254.0}, "class_id": 47, "box_caption": "brakD_S_50 0.001", "scores": {"class_score": 0.0014028549194335938}, "domain": "pixel"}, {"position": {"minX": 494.5, "minY": 274.0, "maxX": 513.5, "maxY": 279.0}, "class_id": 2, "box_caption": "large_D 0.001", "scores": {"class_score": 0.0014009475708007812}, "domain": "pixel"}, {"position": {"minX": 502.0, "minY": 221.25, "maxX": 529.0, "maxY": 254.0}, "class_id": 10, "box_caption": "team_crew 0.001", "scores": {"class_score": 0.0013971328735351562}, "domain": "pixel"}, {"position": {"minX": 502.0, "minY": 221.25, "maxX": 529.0, "maxY": 254.0}, "class_id": 30, "box_caption": "rraid_Dakar 0.001", "scores": {"class_score": 0.0013971328735351562}, "domain": "pixel"}, {"position": {"minX": 502.0, "minY": 221.25, "maxX": 529.0, "maxY": 254.0}, "class_id": 56, "box_caption": "chocabs_wall 0.001", "scores": {"class_score": 0.0013971328735351562}, "domain": "pixel"}, {"position": {"minX": 502.0, "minY": 221.25, "maxX": 529.0, "maxY": 254.0}, "class_id": 75, "box_caption": "car 0.001", "scores": {"class_score": 0.0013971328735351562}, "domain": "pixel"}, {"position": {"minX": 502.0, "minY": 221.25, "maxX": 529.0, "maxY": 254.0}, "class_id": 8, "box_caption": "pilot_injured 0.001", "scores": {"class_score": 0.0013914108276367188}, "domain": "pixel"}, {"position": {"minX": 502.0, "minY": 221.25, "maxX": 529.0, "maxY": 254.0}, "class_id": 31, "box_caption": "rraid_Baja 0.001", "scores": {"class_score": 0.0013914108276367188}, "domain": "pixel"}, {"position": {"minX": 502.0, "minY": 221.25, "maxX": 529.0, "maxY": 254.0}, "class_id": 32, "box_caption": "rraid_XE 0.001", "scores": {"class_score": 0.0013914108276367188}, "domain": "pixel"}, {"position": {"minX": 502.0, "minY": 221.25, "maxX": 529.0, "maxY": 254.0}, "class_id": 59, "box_caption": "grass 0.001", "scores": {"class_score": 0.0013914108276367188}, "domain": "pixel"}, {"position": {"minX": 501.75, "minY": 221.5, "maxX": 529.0, "maxY": 254.0}, "class_id": 55, "box_caption": "conc_wall 0.001", "scores": {"class_score": 0.0013904571533203125}, "domain": "pixel"}, {"position": {"minX": 502.0, "minY": 221.25, "maxX": 529.0, "maxY": 254.0}, "class_id": 5, "box_caption": "pilot_racing 0.001", "scores": {"class_score": 0.0013866424560546875}, "domain": "pixel"}, {"position": {"minX": 502.0, "minY": 221.25, "maxX": 529.0, "maxY": 254.0}, "class_id": 7, "box_caption": "pilot_sliding 0.001", "scores": {"class_score": 0.0013866424560546875}, "domain": "pixel"}, {"position": {"minX": 502.0, "minY": 221.25, "maxX": 529.0, "maxY": 254.0}, "class_id": 44, "box_caption": "red_lights 0.001", "scores": {"class_score": 0.0013866424560546875}, "domain": "pixel"}, {"position": {"minX": 502.0, "minY": 221.25, "maxX": 529.0, "maxY": 254.0}, "class_id": 60, "box_caption": "cones 0.001", "scores": {"class_score": 0.0013866424560546875}, "domain": "pixel"}, {"position": {"minX": 501.75, "minY": 221.5, "maxX": 529.0, "maxY": 254.0}, "class_id": 68, "box_caption": "barrier_tape 0.001", "scores": {"class_score": 0.001384735107421875}, "domain": "pixel"}, {"position": {"minX": 502.0, "minY": 221.25, "maxX": 529.0, "maxY": 254.0}, "class_id": 12, "box_caption": "helmet_full 0.001", "scores": {"class_score": 0.00138092041015625}, "domain": "pixel"}, {"position": {"minX": 502.0, "minY": 221.25, "maxX": 529.0, "maxY": 254.0}, "class_id": 43, "box_caption": "green_lights 0.001", "scores": {"class_score": 0.00138092041015625}, "domain": "pixel"}, {"position": {"minX": 502.0, "minY": 221.25, "maxX": 529.0, "maxY": 254.0}, "class_id": 46, "box_caption": "gravel 0.001", "scores": {"class_score": 0.00138092041015625}, "domain": "pixel"}, {"position": {"minX": 502.0, "minY": 221.25, "maxX": 529.0, "maxY": 254.0}, "class_id": 48, "box_caption": "brakD_S_100 0.001", "scores": {"class_score": 0.00138092041015625}, "domain": "pixel"}, {"position": {"minX": 502.0, "minY": 221.25, "maxX": 529.0, "maxY": 254.0}, "class_id": 53, "box_caption": "lines 0.001", "scores": {"class_score": 0.00138092041015625}, "domain": "pixel"}, {"position": {"minX": 502.0, "minY": 221.25, "maxX": 529.0, "maxY": 254.0}, "class_id": 54, "box_caption": "start_fin_line 0.001", "scores": {"class_score": 0.00138092041015625}, "domain": "pixel"}, {"position": {"minX": 502.0, "minY": 221.25, "maxX": 529.0, "maxY": 254.0}, "class_id": 66, "box_caption": "hole 0.001", "scores": {"class_score": 0.00138092041015625}, "domain": "pixel"}, {"position": {"minX": 502.0, "minY": 221.25, "maxX": 529.0, "maxY": 254.0}, "class_id": 74, "box_caption": "house 0.001", "scores": {"class_score": 0.00138092041015625}, "domain": "pixel"}, {"position": {"minX": 501.75, "minY": 221.5, "maxX": 529.0, "maxY": 254.0}, "class_id": 26, "box_caption": "wtcr 0.001", "scores": {"class_score": 0.0013790130615234375}, "domain": "pixel"}, {"position": {"minX": 501.75, "minY": 221.5, "maxX": 529.0, "maxY": 254.0}, "class_id": 23, "box_caption": "Indy 0.001", "scores": {"class_score": 0.0013742446899414062}, "domain": "pixel"}, {"position": {"minX": 502.0, "minY": 221.25, "maxX": 529.0, "maxY": 254.0}, "class_id": 13, "box_caption": "helmet_open 0.001", "scores": {"class_score": 0.0013704299926757812}, "domain": "pixel"}, {"position": {"minX": 502.0, "minY": 221.25, "maxX": 529.0, "maxY": 254.0}, "class_id": 45, "box_caption": "tarmac 0.001", "scores": {"class_score": 0.0013704299926757812}, "domain": "pixel"}, {"position": {"minX": 502.0, "minY": 221.25, "maxX": 529.0, "maxY": 254.0}, "class_id": 50, "box_caption": "apex 0.001", "scores": {"class_score": 0.0013704299926757812}, "domain": "pixel"}, {"position": {"minX": 502.0, "minY": 221.25, "maxX": 529.0, "maxY": 254.0}, "class_id": 57, "box_caption": "fencing 0.001", "scores": {"class_score": 0.0013704299926757812}, "domain": "pixel"}, {"position": {"minX": 502.0, "minY": 221.25, "maxX": 529.0, "maxY": 254.0}, "class_id": 69, "box_caption": "wall 0.001", "scores": {"class_score": 0.0013704299926757812}, "domain": "pixel"}, {"position": {"minX": 502.0, "minY": 221.25, "maxX": 529.0, "maxY": 254.0}, "class_id": 25, "box_caption": "GT 0.001", "scores": {"class_score": 0.00136566162109375}, "domain": "pixel"}, {"position": {"minX": 502.0, "minY": 221.25, "maxX": 529.0, "maxY": 254.0}, "class_id": 62, "box_caption": "oil 0.001", "scores": {"class_score": 0.00136566162109375}, "domain": "pixel"}, {"position": {"minX": 501.75, "minY": 221.5, "maxX": 529.0, "maxY": 254.0}, "class_id": 17, "box_caption": "moto_x 0.001", "scores": {"class_score": 0.0013637542724609375}, "domain": "pixel"}, {"position": {"minX": 502.0, "minY": 221.25, "maxX": 529.0, "maxY": 254.0}, "class_id": 19, "box_caption": "F2 0.001", "scores": {"class_score": 0.0013599395751953125}, "domain": "pixel"}, {"position": {"minX": 502.0, "minY": 221.25, "maxX": 529.0, "maxY": 254.0}, "class_id": 22, "box_caption": "FE 0.001", "scores": {"class_score": 0.0013599395751953125}, "domain": "pixel"}, {"position": {"minX": 502.0, "minY": 221.25, "maxX": 529.0, "maxY": 254.0}, "class_id": 39, "box_caption": "blue_flag 0.001", "scores": {"class_score": 0.0013599395751953125}, "domain": "pixel"}, {"position": {"minX": 502.0, "minY": 221.25, "maxX": 529.0, "maxY": 254.0}, "class_id": 49, "box_caption": "brakD_S_150 0.001", "scores": {"class_score": 0.0013599395751953125}, "domain": "pixel"}, {"position": {"minX": 502.0, "minY": 221.25, "maxX": 529.0, "maxY": 254.0}, "class_id": 52, "box_caption": "lane 0.001", "scores": {"class_score": 0.0013599395751953125}, "domain": "pixel"}, {"position": {"minX": 501.75, "minY": 221.5, "maxX": 529.0, "maxY": 254.0}, "class_id": 72, "box_caption": "stone 0.001", "scores": {"class_score": 0.0013580322265625}, "domain": "pixel"}, {"position": {"minX": 502.0, "minY": 221.25, "maxX": 529.0, "maxY": 254.0}, "class_id": 11, "box_caption": "spectator 0.001", "scores": {"class_score": 0.0013551712036132812}, "domain": "pixel"}, {"position": {"minX": 502.0, "minY": 221.25, "maxX": 529.0, "maxY": 254.0}, "class_id": 15, "box_caption": "safety_car 0.001", "scores": {"class_score": 0.0013551712036132812}, "domain": "pixel"}, {"position": {"minX": 502.0, "minY": 221.25, "maxX": 529.0, "maxY": 254.0}, "class_id": 21, "box_caption": "F4 0.001", "scores": {"class_score": 0.0013551712036132812}, "domain": "pixel"}, {"position": {"minX": 501.75, "minY": 221.5, "maxX": 529.0, "maxY": 254.0}, "class_id": 28, "box_caption": "wrx 0.001", "scores": {"class_score": 0.0013523101806640625}, "domain": "pixel"}, {"position": {"minX": 502.0, "minY": 221.25, "maxX": 529.0, "maxY": 254.0}, "class_id": 6, "box_caption": "pilot_falling 0.001", "scores": {"class_score": 0.0013494491577148438}, "domain": "pixel"}, {"position": {"minX": 502.0, "minY": 221.25, "maxX": 529.0, "maxY": 254.0}, "class_id": 9, "box_caption": "marshall 0.001", "scores": {"class_score": 0.0013494491577148438}, "domain": "pixel"}, {"position": {"minX": 502.0, "minY": 221.25, "maxX": 529.0, "maxY": 254.0}, "class_id": 36, "box_caption": "yellow_flag 0.001", "scores": {"class_score": 0.0013494491577148438}, "domain": "pixel"}, {"position": {"minX": 502.0, "minY": 221.25, "maxX": 529.0, "maxY": 254.0}, "class_id": 41, "box_caption": "blackwhite_F 0.001", "scores": {"class_score": 0.0013494491577148438}, "domain": "pixel"}, {"position": {"minX": 502.0, "minY": 221.25, "maxX": 529.0, "maxY": 254.0}, "class_id": 70, "box_caption": "dune 0.001", "scores": {"class_score": 0.0013494491577148438}, "domain": "pixel"}, {"position": {"minX": 501.75, "minY": 221.5, "maxX": 529.0, "maxY": 254.0}, "class_id": 24, "box_caption": "LMP 0.001", "scores": {"class_score": 0.0013475418090820312}, "domain": "pixel"}, {"position": {"minX": 269.25, "minY": 69.5625, "maxX": 321.75, "maxY": 99.9375}, "class_id": 40, "box_caption": "black_flag 0.001", "scores": {"class_score": 0.0013437271118164062}, "domain": "pixel"}, {"position": {"minX": 502.0, "minY": 221.25, "maxX": 529.0, "maxY": 254.0}, "class_id": 34, "box_caption": "sprint_car 0.001", "scores": {"class_score": 0.0013437271118164062}, "domain": "pixel"}, {"position": {"minX": 502.0, "minY": 221.25, "maxX": 529.0, "maxY": 254.0}, "class_id": 67, "box_caption": "jump 0.001", "scores": {"class_score": 0.0013437271118164062}, "domain": "pixel"}, {"position": {"minX": 502.0, "minY": 221.25, "maxX": 529.0, "maxY": 254.0}, "class_id": 42, "box_caption": "chequered_F 0.001", "scores": {"class_score": 0.001338958740234375}, "domain": "pixel"}, {"position": {"minX": 502.0, "minY": 221.25, "maxX": 529.0, "maxY": 254.0}, "class_id": 51, "box_caption": "kerbs 0.001", "scores": {"class_score": 0.001338958740234375}, "domain": "pixel"}, {"position": {"minX": 501.75, "minY": 221.5, "maxX": 529.0, "maxY": 254.0}, "class_id": 65, "box_caption": "snow_ice 0.001", "scores": {"class_score": 0.0013370513916015625}, "domain": "pixel"}, {"position": {"minX": 149.125, "minY": 213.875, "maxX": 155.625, "maxY": 235.875}, "class_id": 1, "box_caption": "small_D 0.001", "scores": {"class_score": 0.0013360977172851562}, "domain": "pixel"}, {"position": {"minX": 269.25, "minY": 69.5625, "maxX": 321.75, "maxY": 99.9375}, "class_id": 71, "box_caption": "tree 0.001", "scores": {"class_score": 0.0013332366943359375}, "domain": "pixel"}, {"position": {"minX": 501.75, "minY": 221.5, "maxX": 529.0, "maxY": 254.0}, "class_id": 1, "box_caption": "small_D 0.001", "scores": {"class_score": 0.001331329345703125}, "domain": "pixel"}, {"position": {"minX": 502.0, "minY": 221.25, "maxX": 529.0, "maxY": 254.0}, "class_id": 37, "box_caption": "red_flag 0.001", "scores": {"class_score": 0.0013284683227539062}, "domain": "pixel"}, {"position": {"minX": 502.0, "minY": 221.25, "maxX": 529.0, "maxY": 254.0}, "class_id": 63, "box_caption": "mud 0.001", "scores": {"class_score": 0.0013284683227539062}, "domain": "pixel"}, {"position": {"minX": 502.0, "minY": 221.25, "maxX": 529.0, "maxY": 254.0}, "class_id": 76, "box_caption": "lollipop 0.001", "scores": {"class_score": 0.0013284683227539062}, "domain": "pixel"}, {"position": {"minX": 269.25, "minY": 69.5625, "maxX": 321.75, "maxY": 99.9375}, "class_id": 7, "box_caption": "pilot_sliding 0.001", "scores": {"class_score": 0.0013179779052734375}, "domain": "pixel"}, {"position": {"minX": 269.25, "minY": 69.5625, "maxX": 321.75, "maxY": 99.9375}, "class_id": 59, "box_caption": "grass 0.001", "scores": {"class_score": 0.0013179779052734375}, "domain": "pixel"}, {"position": {"minX": 502.0, "minY": 221.25, "maxX": 529.0, "maxY": 254.0}, "class_id": 3, "box_caption": "pilot_standing 0.001", "scores": {"class_score": 0.0013179779052734375}, "domain": "pixel"}, {"position": {"minX": 149.125, "minY": 213.875, "maxX": 155.625, "maxY": 235.875}, "class_id": 16, "box_caption": "moto_gp 0.001", "scores": {"class_score": 0.001316070556640625}, "domain": "pixel"}, {"position": {"minX": 384.0, "minY": 130.625, "maxX": 390.5, "maxY": 141.625}, "class_id": 2, "box_caption": "large_D 0.001", "scores": {"class_score": 0.0013132095336914062}, "domain": "pixel"}, {"position": {"minX": 269.25, "minY": 69.5625, "maxX": 321.75, "maxY": 99.9375}, "class_id": 61, "box_caption": "smock 0.001", "scores": {"class_score": 0.0013132095336914062}, "domain": "pixel"}, {"position": {"minX": 502.0, "minY": 221.25, "maxX": 529.0, "maxY": 254.0}, "class_id": 73, "box_caption": "barrier 0.001", "scores": {"class_score": 0.0013132095336914062}, "domain": "pixel"}, {"position": {"minX": 269.25, "minY": 69.5625, "maxX": 321.75, "maxY": 99.9375}, "class_id": 56, "box_caption": "chocabs_wall 0.001", "scores": {"class_score": 0.0013074874877929688}, "domain": "pixel"}, {"position": {"minX": 269.25, "minY": 69.5625, "maxX": 321.75, "maxY": 99.9375}, "class_id": 64, "box_caption": "sand 0.001", "scores": {"class_score": 0.0013074874877929688}, "domain": "pixel"}, {"position": {"minX": 502.0, "minY": 221.25, "maxX": 529.0, "maxY": 254.0}, "class_id": 27, "box_caption": "wrc 0.001", "scores": {"class_score": 0.0013074874877929688}, "domain": "pixel"}, {"position": {"minX": 501.75, "minY": 221.5, "maxX": 529.0, "maxY": 254.0}, "class_id": 4, "box_caption": "pilot_walking 0.001", "scores": {"class_score": 0.0013055801391601562}, "domain": "pixel"}, {"position": {"minX": 269.25, "minY": 69.5625, "maxX": 321.75, "maxY": 99.9375}, "class_id": 32, "box_caption": "rraid_XE 0.001", "scores": {"class_score": 0.0013027191162109375}, "domain": "pixel"}, {"position": {"minX": 269.25, "minY": 69.5625, "maxX": 321.75, "maxY": 99.9375}, "class_id": 66, "box_caption": "hole 0.001", "scores": {"class_score": 0.0013027191162109375}, "domain": "pixel"}, {"position": {"minX": 501.75, "minY": 221.5, "maxX": 529.0, "maxY": 254.0}, "class_id": 35, "box_caption": "green_flag 0.001", "scores": {"class_score": 0.001300811767578125}, "domain": "pixel"}, {"position": {"minX": 269.25, "minY": 69.5625, "maxX": 321.75, "maxY": 99.9375}, "class_id": 14, "box_caption": "helmet_fullX 0.001", "scores": {"class_score": 0.0012979507446289062}, "domain": "pixel"}, {"position": {"minX": 269.25, "minY": 69.5625, "maxX": 321.75, "maxY": 99.9375}, "class_id": 30, "box_caption": "rraid_Dakar 0.001", "scores": {"class_score": 0.0012979507446289062}, "domain": "pixel"}, {"position": {"minX": 269.25, "minY": 69.5625, "maxX": 321.75, "maxY": 99.9375}, "class_id": 33, "box_caption": "nascar 0.001", "scores": {"class_score": 0.0012979507446289062}, "domain": "pixel"}, {"position": {"minX": 269.25, "minY": 69.5625, "maxX": 321.75, "maxY": 99.9375}, "class_id": 38, "box_caption": "redyellow_F 0.001", "scores": {"class_score": 0.0012979507446289062}, "domain": "pixel"}, {"position": {"minX": 269.25, "minY": 69.5625, "maxX": 321.75, "maxY": 99.9375}, "class_id": 44, "box_caption": "red_lights 0.001", "scores": {"class_score": 0.0012979507446289062}, "domain": "pixel"}, {"position": {"minX": 269.25, "minY": 69.5625, "maxX": 321.75, "maxY": 99.9375}, "class_id": 54, "box_caption": "start_fin_line 0.001", "scores": {"class_score": 0.0012979507446289062}, "domain": "pixel"}, {"position": {"minX": 269.25, "minY": 69.5625, "maxX": 321.75, "maxY": 99.9375}, "class_id": 55, "box_caption": "conc_wall 0.001", "scores": {"class_score": 0.0012979507446289062}, "domain": "pixel"}, {"position": {"minX": 269.25, "minY": 69.5625, "maxX": 321.75, "maxY": 99.9375}, "class_id": 69, "box_caption": "wall 0.001", "scores": {"class_score": 0.0012979507446289062}, "domain": "pixel"}, {"position": {"minX": 269.25, "minY": 69.6875, "maxX": 321.25, "maxY": 99.8125}, "class_id": 29, "box_caption": "wtcr 0.001", "scores": {"class_score": 0.001293182373046875}, "domain": "pixel"}, {"position": {"minX": 16.375, "minY": 254.0, "maxX": 73.6875, "maxY": 278.5}, "class_id": 71, "box_caption": "tree 0.001", "scores": {"class_score": 0.001293182373046875}, "domain": "pixel"}, {"position": {"minX": 27.71875, "minY": 90.1875, "maxX": 73.625, "maxY": 142.5}, "class_id": 70, "box_caption": "dune 0.001", "scores": {"class_score": 0.001293182373046875}, "domain": "pixel"}, {"position": {"minX": 269.25, "minY": 69.5625, "maxX": 321.75, "maxY": 99.9375}, "class_id": 43, "box_caption": "green_lights 0.001", "scores": {"class_score": 0.0012922286987304688}, "domain": "pixel"}, {"position": {"minX": 269.25, "minY": 69.5625, "maxX": 321.75, "maxY": 99.9375}, "class_id": 8, "box_caption": "pilot_injured 0.001", "scores": {"class_score": 0.0012874603271484375}, "domain": "pixel"}, {"position": {"minX": 269.25, "minY": 69.5625, "maxX": 321.75, "maxY": 99.9375}, "class_id": 31, "box_caption": "rraid_Baja 0.001", "scores": {"class_score": 0.0012874603271484375}, "domain": "pixel"}, {"position": {"minX": 269.25, "minY": 69.5625, "maxX": 321.75, "maxY": 99.9375}, "class_id": 46, "box_caption": "gravel 0.001", "scores": {"class_score": 0.0012874603271484375}, "domain": "pixel"}, {"position": {"minX": 269.25, "minY": 69.5625, "maxX": 321.75, "maxY": 99.9375}, "class_id": 62, "box_caption": "oil 0.001", "scores": {"class_score": 0.0012874603271484375}, "domain": "pixel"}, {"position": {"minX": 269.25, "minY": 69.5625, "maxX": 321.75, "maxY": 99.9375}, "class_id": 68, "box_caption": "barrier_tape 0.001", "scores": {"class_score": 0.0012874603271484375}, "domain": "pixel"}, {"position": {"minX": 16.375, "minY": 254.0, "maxX": 73.6875, "maxY": 278.5}, "class_id": 30, "box_caption": "rraid_Dakar 0.001", "scores": {"class_score": 0.0012874603271484375}, "domain": "pixel"}, {"position": {"minX": 16.375, "minY": 254.0, "maxX": 73.6875, "maxY": 278.5}, "class_id": 40, "box_caption": "black_flag 0.001", "scores": {"class_score": 0.0012874603271484375}, "domain": "pixel"}, {"position": {"minX": 16.375, "minY": 254.0, "maxX": 73.6875, "maxY": 278.5}, "class_id": 59, "box_caption": "grass 0.001", "scores": {"class_score": 0.0012874603271484375}, "domain": "pixel"}, {"position": {"minX": 373.5, "minY": 223.25, "maxX": 381.5, "maxY": 236.0}, "class_id": 1, "box_caption": "small_D 0.001", "scores": {"class_score": 0.0012826919555664062}, "domain": "pixel"}, {"position": {"minX": 269.25, "minY": 69.5625, "maxX": 321.75, "maxY": 99.9375}, "class_id": 13, "box_caption": "helmet_open 0.001", "scores": {"class_score": 0.0012826919555664062}, "domain": "pixel"}, {"position": {"minX": 269.25, "minY": 69.5625, "maxX": 321.75, "maxY": 99.9375}, "class_id": 25, "box_caption": "GT 0.001", "scores": {"class_score": 0.0012826919555664062}, "domain": "pixel"}, {"position": {"minX": 502.0, "minY": 221.25, "maxX": 529.0, "maxY": 254.0}, "class_id": 58, "box_caption": "run_off 0.001", "scores": {"class_score": 0.001277923583984375}, "domain": "pixel"}, {"position": {"minX": 16.375, "minY": 254.0, "maxX": 73.6875, "maxY": 278.5}, "class_id": 38, "box_caption": "redyellow_F 0.001", "scores": {"class_score": 0.001277923583984375}, "domain": "pixel"}, {"position": {"minX": 16.375, "minY": 254.0, "maxX": 73.6875, "maxY": 278.5}, "class_id": 61, "box_caption": "smock 0.001", "scores": {"class_score": 0.001277923583984375}, "domain": "pixel"}, {"position": {"minX": 16.375, "minY": 254.0, "maxX": 73.6875, "maxY": 278.5}, "class_id": 64, "box_caption": "sand 0.001", "scores": {"class_score": 0.001277923583984375}, "domain": "pixel"}, {"position": {"minX": 27.71875, "minY": 90.1875, "maxX": 73.625, "maxY": 142.5}, "class_id": 41, "box_caption": "blackwhite_F 0.001", "scores": {"class_score": 0.001277923583984375}, "domain": "pixel"}, {"position": {"minX": 27.71875, "minY": 90.1875, "maxX": 73.625, "maxY": 142.5}, "class_id": 44, "box_caption": "red_lights 0.001", "scores": {"class_score": 0.001277923583984375}, "domain": "pixel"}, {"position": {"minX": 269.25, "minY": 69.5625, "maxX": 321.75, "maxY": 99.9375}, "class_id": 23, "box_caption": "Indy 0.001", "scores": {"class_score": 0.0012769699096679688}, "domain": "pixel"}, {"position": {"minX": 269.25, "minY": 69.5625, "maxX": 321.75, "maxY": 99.9375}, "class_id": 36, "box_caption": "yellow_flag 0.001", "scores": {"class_score": 0.0012769699096679688}, "domain": "pixel"}, {"position": {"minX": 269.25, "minY": 69.5625, "maxX": 321.75, "maxY": 99.9375}, "class_id": 47, "box_caption": "brakD_S_50 0.001", "scores": {"class_score": 0.0012769699096679688}, "domain": "pixel"}, {"position": {"minX": 269.25, "minY": 69.5625, "maxX": 321.75, "maxY": 99.9375}, "class_id": 50, "box_caption": "apex 0.001", "scores": {"class_score": 0.0012769699096679688}, "domain": "pixel"}, {"position": {"minX": 269.25, "minY": 69.5625, "maxX": 321.75, "maxY": 99.9375}, "class_id": 53, "box_caption": "lines 0.001", "scores": {"class_score": 0.0012769699096679688}, "domain": "pixel"}, {"position": {"minX": 269.25, "minY": 69.5625, "maxX": 321.75, "maxY": 99.9375}, "class_id": 75, "box_caption": "car 0.001", "scores": {"class_score": 0.0012769699096679688}, "domain": "pixel"}, {"position": {"minX": 269.25, "minY": 69.5625, "maxX": 321.75, "maxY": 99.9375}, "class_id": 19, "box_caption": "F2 0.001", "scores": {"class_score": 0.0012731552124023438}, "domain": "pixel"}, {"position": {"minX": 269.25, "minY": 69.5625, "maxX": 321.75, "maxY": 99.9375}, "class_id": 26, "box_caption": "wtcr 0.001", "scores": {"class_score": 0.0012731552124023438}, "domain": "pixel"}, {"position": {"minX": 269.25, "minY": 69.5625, "maxX": 321.75, "maxY": 99.9375}, "class_id": 49, "box_caption": "brakD_S_150 0.001", "scores": {"class_score": 0.0012731552124023438}, "domain": "pixel"}, {"position": {"minX": 269.25, "minY": 69.5625, "maxX": 321.75, "maxY": 99.9375}, "class_id": 60, "box_caption": "cones 0.001", "scores": {"class_score": 0.0012731552124023438}, "domain": "pixel"}, {"position": {"minX": 502.0, "minY": 221.25, "maxX": 529.0, "maxY": 254.0}, "class_id": 20, "box_caption": "F3 0.001", "scores": {"class_score": 0.0012722015380859375}, "domain": "pixel"}, {"position": {"minX": 16.375, "minY": 254.0, "maxX": 73.6875, "maxY": 278.5}, "class_id": 56, "box_caption": "chocabs_wall 0.001", "scores": {"class_score": 0.0012722015380859375}, "domain": "pixel"}, {"position": {"minX": 16.375, "minY": 254.0, "maxX": 73.6875, "maxY": 278.5}, "class_id": 69, "box_caption": "wall 0.001", "scores": {"class_score": 0.0012722015380859375}, "domain": "pixel"}, {"position": {"minX": 269.25, "minY": 69.6875, "maxX": 321.25, "maxY": 99.8125}, "class_id": 17, "box_caption": "moto_x 0.001", "scores": {"class_score": 0.0012683868408203125}, "domain": "pixel"}, {"position": {"minX": 269.25, "minY": 69.6875, "maxX": 321.25, "maxY": 99.8125}, "class_id": 45, "box_caption": "tarmac 0.001", "scores": {"class_score": 0.0012683868408203125}, "domain": "pixel"}, {"position": {"minX": 27.71875, "minY": 90.1875, "maxX": 73.625, "maxY": 142.5}, "class_id": 36, "box_caption": "yellow_flag 0.001", "scores": {"class_score": 0.0012683868408203125}, "domain": "pixel"}, {"position": {"minX": 27.71875, "minY": 90.1875, "maxX": 73.625, "maxY": 142.5}, "class_id": 64, "box_caption": "sand 0.001", "scores": {"class_score": 0.0012683868408203125}, "domain": "pixel"}, {"position": {"minX": 269.25, "minY": 69.5625, "maxX": 321.75, "maxY": 99.9375}, "class_id": 10, "box_caption": "team_crew 0.001", "scores": {"class_score": 0.0012674331665039062}, "domain": "pixel"}, {"position": {"minX": 269.25, "minY": 69.5625, "maxX": 321.75, "maxY": 99.9375}, "class_id": 12, "box_caption": "helmet_full 0.001", "scores": {"class_score": 0.0012674331665039062}, "domain": "pixel"}, {"position": {"minX": 269.25, "minY": 69.5625, "maxX": 321.75, "maxY": 99.9375}, "class_id": 39, "box_caption": "blue_flag 0.001", "scores": {"class_score": 0.0012674331665039062}, "domain": "pixel"}, {"position": {"minX": 269.25, "minY": 69.5625, "maxX": 321.75, "maxY": 99.9375}, "class_id": 48, "box_caption": "brakD_S_100 0.001", "scores": {"class_score": 0.0012674331665039062}, "domain": "pixel"}, {"position": {"minX": 269.25, "minY": 69.5625, "maxX": 321.75, "maxY": 99.9375}, "class_id": 76, "box_caption": "lollipop 0.001", "scores": {"class_score": 0.0012674331665039062}, "domain": "pixel"}, {"position": {"minX": 16.375, "minY": 254.0, "maxX": 73.6875, "maxY": 278.5}, "class_id": 7, "box_caption": "pilot_sliding 0.001", "scores": {"class_score": 0.0012674331665039062}, "domain": "pixel"}, {"position": {"minX": 16.375, "minY": 254.0, "maxX": 73.6875, "maxY": 278.5}, "class_id": 29, "box_caption": "wtcr 0.001", "scores": {"class_score": 0.0012674331665039062}, "domain": "pixel"}, {"position": {"minX": 16.375, "minY": 254.0, "maxX": 73.6875, "maxY": 278.5}, "class_id": 31, "box_caption": "rraid_Baja 0.001", "scores": {"class_score": 0.0012674331665039062}, "domain": "pixel"}, {"position": {"minX": 16.375, "minY": 254.0, "maxX": 73.6875, "maxY": 278.5}, "class_id": 32, "box_caption": "rraid_XE 0.001", "scores": {"class_score": 0.0012674331665039062}, "domain": "pixel"}, {"position": {"minX": 16.375, "minY": 254.0, "maxX": 73.6875, "maxY": 278.5}, "class_id": 54, "box_caption": "start_fin_line 0.001", "scores": {"class_score": 0.0012674331665039062}, "domain": "pixel"}, {"position": {"minX": 16.375, "minY": 254.0, "maxX": 73.6875, "maxY": 278.5}, "class_id": 66, "box_caption": "hole 0.001", "scores": {"class_score": 0.0012674331665039062}, "domain": "pixel"}, {"position": {"minX": 421.5, "minY": 185.625, "maxX": 488.0, "maxY": 240.125}, "class_id": 70, "box_caption": "dune 0.001", "scores": {"class_score": 0.0012655258178710938}, "domain": "pixel"}, {"position": {"minX": 269.25, "minY": 69.5625, "maxX": 321.75, "maxY": 99.9375}, "class_id": 22, "box_caption": "FE 0.001", "scores": {"class_score": 0.001262664794921875}, "domain": "pixel"}, {"position": {"minX": 269.25, "minY": 69.5625, "maxX": 321.75, "maxY": 99.9375}, "class_id": 37, "box_caption": "red_flag 0.001", "scores": {"class_score": 0.001262664794921875}, "domain": "pixel"}, {"position": {"minX": 269.25, "minY": 69.5625, "maxX": 321.75, "maxY": 99.9375}, "class_id": 41, "box_caption": "blackwhite_F 0.001", "scores": {"class_score": 0.001262664794921875}, "domain": "pixel"}, {"position": {"minX": 269.25, "minY": 69.5625, "maxX": 321.75, "maxY": 99.9375}, "class_id": 52, "box_caption": "lane 0.001", "scores": {"class_score": 0.001262664794921875}, "domain": "pixel"}, {"position": {"minX": 269.25, "minY": 69.5625, "maxX": 321.75, "maxY": 99.9375}, "class_id": 72, "box_caption": "stone 0.001", "scores": {"class_score": 0.001262664794921875}, "domain": "pixel"}, {"position": {"minX": 16.375, "minY": 254.0, "maxX": 73.6875, "maxY": 278.5}, "class_id": 55, "box_caption": "conc_wall 0.001", "scores": {"class_score": 0.001262664794921875}, "domain": "pixel"}, {"position": {"minX": 373.5, "minY": 223.25, "maxX": 381.5, "maxY": 236.0}, "class_id": 18, "box_caption": "F1 0.001", "scores": {"class_score": 0.0012617111206054688}, "domain": "pixel"}, {"position": {"minX": 269.25, "minY": 69.5625, "maxX": 321.75, "maxY": 99.9375}, "class_id": 5, "box_caption": "pilot_racing 0.001", "scores": {"class_score": 0.0012578964233398438}, "domain": "pixel"}, {"position": {"minX": 269.25, "minY": 69.5625, "maxX": 321.75, "maxY": 99.9375}, "class_id": 21, "box_caption": "F4 0.001", "scores": {"class_score": 0.0012578964233398438}, "domain": "pixel"}, {"position": {"minX": 269.25, "minY": 69.5625, "maxX": 321.75, "maxY": 99.9375}, "class_id": 57, "box_caption": "fencing 0.001", "scores": {"class_score": 0.0012578964233398438}, "domain": "pixel"}, {"position": {"minX": 269.25, "minY": 69.5625, "maxX": 321.75, "maxY": 99.9375}, "class_id": 74, "box_caption": "house 0.001", "scores": {"class_score": 0.0012578964233398438}, "domain": "pixel"}, {"position": {"minX": 16.375, "minY": 254.0, "maxX": 73.6875, "maxY": 278.5}, "class_id": 8, "box_caption": "pilot_injured 0.001", "scores": {"class_score": 0.0012578964233398438}, "domain": "pixel"}, {"position": {"minX": 16.375, "minY": 254.0, "maxX": 73.6875, "maxY": 278.5}, "class_id": 50, "box_caption": "apex 0.001", "scores": {"class_score": 0.0012578964233398438}, "domain": "pixel"}, {"position": {"minX": 16.375, "minY": 254.0, "maxX": 73.6875, "maxY": 278.5}, "class_id": 68, "box_caption": "barrier_tape 0.001", "scores": {"class_score": 0.0012578964233398438}, "domain": "pixel"}, {"position": {"minX": 27.71875, "minY": 90.1875, "maxX": 73.625, "maxY": 142.5}, "class_id": 31, "box_caption": "rraid_Baja 0.001", "scores": {"class_score": 0.0012578964233398438}, "domain": "pixel"}, {"position": {"minX": 269.25, "minY": 69.6875, "maxX": 321.25, "maxY": 99.8125}, "class_id": 70, "box_caption": "dune 0.001", "scores": {"class_score": 0.0012531280517578125}, "domain": "pixel"}, {"position": {"minX": 27.71875, "minY": 90.1875, "maxX": 73.625, "maxY": 142.5}, "class_id": 49, "box_caption": "brakD_S_150 0.001", "scores": {"class_score": 0.0012531280517578125}, "domain": "pixel"}, {"position": {"minX": 16.375, "minY": 254.0, "maxX": 73.6875, "maxY": 278.5}, "class_id": 14, "box_caption": "helmet_fullX 0.001", "scores": {"class_score": 0.0012521743774414062}, "domain": "pixel"}, {"position": {"minX": 16.375, "minY": 254.0, "maxX": 73.6875, "maxY": 278.5}, "class_id": 33, "box_caption": "nascar 0.001", "scores": {"class_score": 0.0012521743774414062}, "domain": "pixel"}, {"position": {"minX": 421.5, "minY": 185.625, "maxX": 488.0, "maxY": 240.125}, "class_id": 41, "box_caption": "blackwhite_F 0.001", "scores": {"class_score": 0.001251220703125}, "domain": "pixel"}, {"position": {"minX": 421.5, "minY": 185.625, "maxX": 488.0, "maxY": 240.125}, "class_id": 44, "box_caption": "red_lights 0.001", "scores": {"class_score": 0.001251220703125}, "domain": "pixel"}, {"position": {"minX": 80.4375, "minY": 198.375, "maxX": 90.6875, "maxY": 201.375}, "class_id": 0, "box_caption": "medium_D 0.001", "scores": {"class_score": 0.0012493133544921875}, "domain": "pixel"}, {"position": {"minX": 269.25, "minY": 69.6875, "maxX": 321.25, "maxY": 99.8125}, "class_id": 28, "box_caption": "wrx 0.001", "scores": {"class_score": 0.0012483596801757812}, "domain": "pixel"}, {"position": {"minX": 16.375, "minY": 254.0, "maxX": 73.6875, "maxY": 278.5}, "class_id": 13, "box_caption": "helmet_open 0.001", "scores": {"class_score": 0.0012483596801757812}, "domain": "pixel"}, {"position": {"minX": 16.375, "minY": 254.0, "maxX": 73.6875, "maxY": 278.5}, "class_id": 47, "box_caption": "brakD_S_50 0.001", "scores": {"class_score": 0.0012483596801757812}, "domain": "pixel"}, {"position": {"minX": 16.375, "minY": 254.0, "maxX": 73.6875, "maxY": 278.5}, "class_id": 53, "box_caption": "lines 0.001", "scores": {"class_score": 0.0012483596801757812}, "domain": "pixel"}, {"position": {"minX": 27.71875, "minY": 90.1875, "maxX": 73.625, "maxY": 142.5}, "class_id": 17, "box_caption": "moto_x 0.001", "scores": {"class_score": 0.0012483596801757812}, "domain": "pixel"}, {"position": {"minX": 269.25, "minY": 69.5625, "maxX": 321.75, "maxY": 99.9375}, "class_id": 6, "box_caption": "pilot_falling 0.001", "scores": {"class_score": 0.001247406005859375}, "domain": "pixel"}, {"position": {"minX": 269.25, "minY": 69.5625, "maxX": 321.75, "maxY": 99.9375}, "class_id": 9, "box_caption": "marshall 0.001", "scores": {"class_score": 0.001247406005859375}, "domain": "pixel"}, {"position": {"minX": 269.25, "minY": 69.5625, "maxX": 321.75, "maxY": 99.9375}, "class_id": 11, "box_caption": "spectator 0.001", "scores": {"class_score": 0.001247406005859375}, "domain": "pixel"}, {"position": {"minX": 421.5, "minY": 185.625, "maxX": 488.0, "maxY": 240.125}, "class_id": 64, "box_caption": "sand 0.001", "scores": {"class_score": 0.0012454986572265625}, "domain": "pixel"}, {"position": {"minX": 81.0625, "minY": 198.875, "maxX": 92.1875, "maxY": 202.125}, "class_id": 1, "box_caption": "small_D 0.001", "scores": {"class_score": 0.0012445449829101562}, "domain": "pixel"}, {"position": {"minX": 269.25, "minY": 69.5625, "maxX": 321.75, "maxY": 99.9375}, "class_id": 42, "box_caption": "chequered_F 0.001", "scores": {"class_score": 0.00124359130859375}, "domain": "pixel"}, {"position": {"minX": 27.71875, "minY": 90.1875, "maxX": 73.625, "maxY": 142.5}, "class_id": 13, "box_caption": "helmet_open 0.001", "scores": {"class_score": 0.00124359130859375}, "domain": "pixel"}, {"position": {"minX": 27.71875, "minY": 90.1875, "maxX": 73.625, "maxY": 142.5}, "class_id": 53, "box_caption": "lines 0.001", "scores": {"class_score": 0.00124359130859375}, "domain": "pixel"}, {"position": {"minX": 27.71875, "minY": 90.1875, "maxX": 73.625, "maxY": 142.5}, "class_id": 59, "box_caption": "grass 0.001", "scores": {"class_score": 0.00124359130859375}, "domain": "pixel"}, {"position": {"minX": 16.375, "minY": 254.0, "maxX": 73.6875, "maxY": 278.5}, "class_id": 10, "box_caption": "team_crew 0.001", "scores": {"class_score": 0.0012426376342773438}, "domain": "pixel"}, {"position": {"minX": 16.375, "minY": 254.0, "maxX": 73.6875, "maxY": 278.5}, "class_id": 19, "box_caption": "F2 0.001", "scores": {"class_score": 0.0012426376342773438}, "domain": "pixel"}, {"position": {"minX": 16.375, "minY": 254.0, "maxX": 73.6875, "maxY": 278.5}, "class_id": 26, "box_caption": "wtcr 0.001", "scores": {"class_score": 0.0012426376342773438}, "domain": "pixel"}, {"position": {"minX": 16.375, "minY": 254.0, "maxX": 73.6875, "maxY": 278.5}, "class_id": 37, "box_caption": "red_flag 0.001", "scores": {"class_score": 0.0012426376342773438}, "domain": "pixel"}, {"position": {"minX": 16.375, "minY": 254.0, "maxX": 73.6875, "maxY": 278.5}, "class_id": 43, "box_caption": "green_lights 0.001", "scores": {"class_score": 0.0012426376342773438}, "domain": "pixel"}, {"position": {"minX": 16.375, "minY": 254.0, "maxX": 73.6875, "maxY": 278.5}, "class_id": 46, "box_caption": "gravel 0.001", "scores": {"class_score": 0.0012426376342773438}, "domain": "pixel"}, {"position": {"minX": 16.375, "minY": 254.0, "maxX": 73.6875, "maxY": 278.5}, "class_id": 52, "box_caption": "lane 0.001", "scores": {"class_score": 0.0012426376342773438}, "domain": "pixel"}, {"position": {"minX": 16.375, "minY": 254.0, "maxX": 73.6875, "maxY": 278.5}, "class_id": 75, "box_caption": "car 0.001", "scores": {"class_score": 0.0012426376342773438}, "domain": "pixel"}, {"position": {"minX": 421.5, "minY": 185.625, "maxX": 488.0, "maxY": 240.125}, "class_id": 36, "box_caption": "yellow_flag 0.001", "scores": {"class_score": 0.0012416839599609375}, "domain": "pixel"}, {"position": {"minX": 16.375, "minY": 254.0, "maxX": 73.6875, "maxY": 278.5}, "class_id": 23, "box_caption": "Indy 0.001", "scores": {"class_score": 0.0012388229370117188}, "domain": "pixel"}, {"position": {"minX": 16.375, "minY": 254.0, "maxX": 73.6875, "maxY": 278.5}, "class_id": 25, "box_caption": "GT 0.001", "scores": {"class_score": 0.0012388229370117188}, "domain": "pixel"}, {"position": {"minX": 16.375, "minY": 254.0, "maxX": 73.6875, "maxY": 278.5}, "class_id": 44, "box_caption": "red_lights 0.001", "scores": {"class_score": 0.0012388229370117188}, "domain": "pixel"}, {"position": {"minX": 16.375, "minY": 254.0, "maxX": 73.6875, "maxY": 278.5}, "class_id": 48, "box_caption": "brakD_S_100 0.001", "scores": {"class_score": 0.0012388229370117188}, "domain": "pixel"}, {"position": {"minX": 27.71875, "minY": 90.1875, "maxX": 73.625, "maxY": 142.5}, "class_id": 4, "box_caption": "pilot_walking 0.001", "scores": {"class_score": 0.0012388229370117188}, "domain": "pixel"}, {"position": {"minX": 27.71875, "minY": 90.1875, "maxX": 73.625, "maxY": 142.5}, "class_id": 10, "box_caption": "team_crew 0.001", "scores": {"class_score": 0.0012388229370117188}, "domain": "pixel"}, {"position": {"minX": 27.71875, "minY": 90.1875, "maxX": 73.625, "maxY": 142.5}, "class_id": 21, "box_caption": "F4 0.001", "scores": {"class_score": 0.0012388229370117188}, "domain": "pixel"}, {"position": {"minX": 27.71875, "minY": 90.1875, "maxX": 73.625, "maxY": 142.5}, "class_id": 69, "box_caption": "wall 0.001", "scores": {"class_score": 0.0012388229370117188}, "domain": "pixel"}, {"position": {"minX": 269.25, "minY": 69.5625, "maxX": 321.75, "maxY": 99.9375}, "class_id": 1, "box_caption": "small_D 0.001", "scores": {"class_score": 0.0012378692626953125}, "domain": "pixel"}, {"position": {"minX": 269.25, "minY": 69.5625, "maxX": 321.75, "maxY": 99.9375}, "class_id": 15, "box_caption": "safety_car 0.001", "scores": {"class_score": 0.0012378692626953125}, "domain": "pixel"}, {"position": {"minX": 269.25, "minY": 69.6875, "maxX": 321.25, "maxY": 99.8125}, "class_id": 24, "box_caption": "LMP 0.001", "scores": {"class_score": 0.0012331008911132812}, "domain": "pixel"}, {"position": {"minX": 269.25, "minY": 69.5625, "maxX": 321.75, "maxY": 99.9375}, "class_id": 34, "box_caption": "sprint_car 0.001", "scores": {"class_score": 0.0012331008911132812}, "domain": "pixel"}, {"position": {"minX": 269.25, "minY": 69.5625, "maxX": 321.75, "maxY": 99.9375}, "class_id": 65, "box_caption": "snow_ice 0.001", "scores": {"class_score": 0.0012331008911132812}, "domain": "pixel"}, {"position": {"minX": 16.375, "minY": 254.0, "maxX": 73.6875, "maxY": 278.5}, "class_id": 36, "box_caption": "yellow_flag 0.001", "scores": {"class_score": 0.0012331008911132812}, "domain": "pixel"}, {"position": {"minX": 16.375, "minY": 254.0, "maxX": 73.6875, "maxY": 278.5}, "class_id": 41, "box_caption": "blackwhite_F 0.001", "scores": {"class_score": 0.0012331008911132812}, "domain": "pixel"}, {"position": {"minX": 16.375, "minY": 254.0, "maxX": 73.6875, "maxY": 278.5}, "class_id": 49, "box_caption": "brakD_S_150 0.001", "scores": {"class_score": 0.0012331008911132812}, "domain": "pixel"}, {"position": {"minX": 16.375, "minY": 254.0, "maxX": 73.6875, "maxY": 278.5}, "class_id": 60, "box_caption": "cones 0.001", "scores": {"class_score": 0.0012331008911132812}, "domain": "pixel"}, {"position": {"minX": 27.71875, "minY": 90.1875, "maxX": 73.625, "maxY": 142.5}, "class_id": 8, "box_caption": "pilot_injured 0.001", "scores": {"class_score": 0.0012331008911132812}, "domain": "pixel"}, {"position": {"minX": 27.71875, "minY": 90.1875, "maxX": 73.625, "maxY": 142.5}, "class_id": 19, "box_caption": "F2 0.001", "scores": {"class_score": 0.0012331008911132812}, "domain": "pixel"}, {"position": {"minX": 27.71875, "minY": 90.1875, "maxX": 73.625, "maxY": 142.5}, "class_id": 30, "box_caption": "rraid_Dakar 0.001", "scores": {"class_score": 0.0012331008911132812}, "domain": "pixel"}, {"position": {"minX": 27.71875, "minY": 90.1875, "maxX": 73.625, "maxY": 142.5}, "class_id": 32, "box_caption": "rraid_XE 0.001", "scores": {"class_score": 0.0012331008911132812}, "domain": "pixel"}, {"position": {"minX": 27.71875, "minY": 90.1875, "maxX": 73.625, "maxY": 142.5}, "class_id": 40, "box_caption": "black_flag 0.001", "scores": {"class_score": 0.0012331008911132812}, "domain": "pixel"}, {"position": {"minX": 27.71875, "minY": 90.1875, "maxX": 73.625, "maxY": 142.5}, "class_id": 73, "box_caption": "barrier 0.001", "scores": {"class_score": 0.0012331008911132812}, "domain": "pixel"}, {"position": {"minX": 16.234375, "minY": 254.25, "maxX": 73.875, "maxY": 278.75}, "class_id": 17, "box_caption": "moto_x 0.001", "scores": {"class_score": 0.001232147216796875}, "domain": "pixel"}, {"position": {"minX": 269.25, "minY": 69.5625, "maxX": 321.75, "maxY": 99.9375}, "class_id": 3, "box_caption": "pilot_standing 0.001", "scores": {"class_score": 0.0012292861938476562}, "domain": "pixel"}, {"position": {"minX": 16.375, "minY": 254.0, "maxX": 73.6875, "maxY": 278.5}, "class_id": 1, "box_caption": "small_D 0.001", "scores": {"class_score": 0.0012292861938476562}, "domain": "pixel"}, {"position": {"minX": 16.375, "minY": 254.0, "maxX": 73.6875, "maxY": 278.5}, "class_id": 57, "box_caption": "fencing 0.001", "scores": {"class_score": 0.0012292861938476562}, "domain": "pixel"}, {"position": {"minX": 16.375, "minY": 254.0, "maxX": 73.6875, "maxY": 278.5}, "class_id": 62, "box_caption": "oil 0.001", "scores": {"class_score": 0.0012292861938476562}, "domain": "pixel"}, {"position": {"minX": 16.375, "minY": 254.0, "maxX": 73.6875, "maxY": 278.5}, "class_id": 74, "box_caption": "house 0.001", "scores": {"class_score": 0.0012292861938476562}, "domain": "pixel"}, {"position": {"minX": 16.375, "minY": 254.0, "maxX": 73.6875, "maxY": 278.5}, "class_id": 76, "box_caption": "lollipop 0.001", "scores": {"class_score": 0.0012292861938476562}, "domain": "pixel"}, {"position": {"minX": 27.71875, "minY": 90.1875, "maxX": 73.625, "maxY": 142.5}, "class_id": 26, "box_caption": "wtcr 0.001", "scores": {"class_score": 0.0012292861938476562}, "domain": "pixel"}, {"position": {"minX": 27.71875, "minY": 90.1875, "maxX": 73.625, "maxY": 142.5}, "class_id": 54, "box_caption": "start_fin_line 0.001", "scores": {"class_score": 0.0012292861938476562}, "domain": "pixel"}, {"position": {"minX": 27.71875, "minY": 90.1875, "maxX": 73.625, "maxY": 142.5}, "class_id": 56, "box_caption": "chocabs_wall 0.001", "scores": {"class_score": 0.0012292861938476562}, "domain": "pixel"}, {"position": {"minX": 27.71875, "minY": 90.1875, "maxX": 73.625, "maxY": 142.5}, "class_id": 65, "box_caption": "snow_ice 0.001", "scores": {"class_score": 0.0012292861938476562}, "domain": "pixel"}, {"position": {"minX": 27.71875, "minY": 90.1875, "maxX": 73.625, "maxY": 142.5}, "class_id": 67, "box_caption": "jump 0.001", "scores": {"class_score": 0.0012292861938476562}, "domain": "pixel"}, {"position": {"minX": 421.5, "minY": 185.625, "maxX": 488.0, "maxY": 240.125}, "class_id": 17, "box_caption": "moto_x 0.001", "scores": {"class_score": 0.0012273788452148438}, "domain": "pixel"}, {"position": {"minX": 421.5, "minY": 185.625, "maxX": 488.0, "maxY": 240.125}, "class_id": 31, "box_caption": "rraid_Baja 0.001", "scores": {"class_score": 0.0012273788452148438}, "domain": "pixel"}, {"position": {"minX": 27.53125, "minY": 90.25, "maxX": 74.0, "maxY": 142.25}, "class_id": 29, "box_caption": "wtcr 0.001", "scores": {"class_score": 0.0012254714965820312}, "domain": "pixel"}, {"position": {"minX": 27.53125, "minY": 90.25, "maxX": 74.0, "maxY": 142.25}, "class_id": 71, "box_caption": "tree 0.001", "scores": {"class_score": 0.0012254714965820312}, "domain": "pixel"}, {"position": {"minX": 27.71875, "minY": 90.1875, "maxX": 73.625, "maxY": 142.5}, "class_id": 5, "box_caption": "pilot_racing 0.001", "scores": {"class_score": 0.001224517822265625}, "domain": "pixel"}, {"position": {"minX": 27.71875, "minY": 90.1875, "maxX": 73.625, "maxY": 142.5}, "class_id": 6, "box_caption": "pilot_falling 0.001", "scores": {"class_score": 0.001224517822265625}, "domain": "pixel"}], "class_labels": {"0": "medium_D", "1": "small_D", "2": "large_D", "3": "pilot_standing", "4": "pilot_walking", "5": "pilot_racing", "6": "pilot_falling", "7": "pilot_sliding", "8": "pilot_injured", "9": "marshall", "10": "team_crew", "11": "spectator", "12": "helmet_full", "13": "helmet_open", "14": "helmet_fullX", "15": "safety_car", "16": "moto_gp", "17": "moto_x", "18": "F1", "19": "F2", "20": "F3", "21": "F4", "22": "FE", "23": "Indy", "24": "LMP", "25": "GT", "26": "wtcr", "27": "wrc", "28": "wrx", "29": "wtcr", "30": "rraid_Dakar", "31": "rraid_Baja", "32": "rraid_XE", "33": "nascar", "34": "sprint_car", "35": "green_flag", "36": "yellow_flag", "37": "red_flag", "38": "redyellow_F", "39": "blue_flag", "40": "black_flag", "41": "blackwhite_F", "42": "chequered_F", "43": "green_lights", "44": "red_lights", "45": "tarmac", "46": "gravel", "47": "brakD_S_50", "48": "brakD_S_100", "49": "brakD_S_150", "50": "apex", "51": "kerbs", "52": "lane", "53": "lines", "54": "start_fin_line", "55": "conc_wall", "56": "chocabs_wall", "57": "fencing", "58": "run_off", "59": "grass", "60": "cones", "61": "smock", "62": "oil", "63": "mud", "64": "sand", "65": "snow_ice", "66": "hole", "67": "jump", "68": "barrier_tape", "69": "wall", "70": "dune", "71": "tree", "72": "stone", "73": "barrier", "74": "house", "75": "car", "76": "lollipop"}}